Workbook

Sheet Resumen
A1: Árbol | B1: Focos | C1: Días | D1: Poder político | E1: Estabilidad (%) | F1: Apoyo a la guerra (%) | G1: Mano de obra | H1: Exp. ejército | I1: Exp. naval | J1: Exp. aérea | K1: Casillas de investigación | L1: Bonos de tecnología (usos) | M1: Fábricas civiles | N1: Fábricas militares | O1: Astilleros | P1: Infraestructura | Q1: Otros edificios (niveles) | R1: Equipo (unidades) | S1: Divisiones | T1: Cazas gratis | U1: Reclamos, núcleos y objetivos | V1: Espíritus (agregados) | W1: Puntaje en el acto (Pesos) | X1: Puntaje de espíritus (Espíritus) | Y1: Puntaje total | Z1: Total vs promedio de potencias | AA1: Focos excluyentes (se cuentan igual)
A2: EFE | B2: =COUNTIF('Por foco'!$A$2:$A$579,$A2) -> 70 | C2: =SUMIFS('Por foco'!$E$2:$E$579,'Por foco'!$A$2:$A$579,$A2) -> 4487 | D2: =SUMIFS('Por foco'!$F$2:$F$579,'Por foco'!$A$2:$A$579,$A2) -> 1470 | E2: =SUMIFS('Por foco'!$G$2:$G$579,'Por foco'!$A$2:$A$579,$A2) -> 0 | F2: =SUMIFS('Por foco'!$H$2:$H$579,'Por foco'!$A$2:$A$579,$A2) -> 15 | G2: =SUMIFS('Por foco'!$I$2:$I$579,'Por foco'!$A$2:$A$579,$A2) -> 80000 | H2: =SUMIFS('Por foco'!$J$2:$J$579,'Por foco'!$A$2:$A$579,$A2) -> 100 | I2: =SUMIFS('Por foco'!$K$2:$K$579,'Por foco'!$A$2:$A$579,$A2) -> 0 | J2: =SUMIFS('Por foco'!$L$2:$L$579,'Por foco'!$A$2:$A$579,$A2) -> 75 | K2: =SUMIFS('Por foco'!$M$2:$M$579,'Por foco'!$A$2:$A$579,$A2) -> 2 | L2: =SUMIFS('Por foco'!$N$2:$N$579,'Por foco'!$A$2:$A$579,$A2) -> 16 | M2: =SUMIFS('Por foco'!$O$2:$O$579,'Por foco'!$A$2:$A$579,$A2) -> 17 | N2: =SUMIFS('Por foco'!$P$2:$P$579,'Por foco'!$A$2:$A$579,$A2) -> 7 | O2: =SUMIFS('Por foco'!$Q$2:$Q$579,'Por foco'!$A$2:$A$579,$A2) -> 4 | P2: =SUMIFS('Por foco'!$R$2:$R$579,'Por foco'!$A$2:$A$579,$A2) -> 0 | Q2: =SUMIFS('Por foco'!$S$2:$S$579,'Por foco'!$A$2:$A$579,$A2) -> 2 | R2: =SUMIFS('Por foco'!$T$2:$T$579,'Por foco'!$A$2:$A$579,$A2) -> 0 | S2: =SUMIFS('Por foco'!$U$2:$U$579,'Por foco'!$A$2:$A$579,$A2) -> 0 | T2: =SUMIFS('Por foco'!$V$2:$V$579,'Por foco'!$A$2:$A$579,$A2) -> 150 | U2: =SUMIFS('Por foco'!$W$2:$W$579,'Por foco'!$A$2:$A$579,$A2) -> 11 | V2: =SUMIFS('Por foco'!$X$2:$X$579,'Por foco'!$A$2:$A$579,$A2) -> 29 | W2: =C2*Pesos!$B$2+D2*Pesos!$B$3+E2*Pesos!$B$4+F2*Pesos!$B$5+G2*Pesos!$B$6+H2*Pesos!$B$7+I2*Pesos!$B$8+J2*Pesos!$B$9+K2*Pesos!$B$10+L2*Pesos!$B$11+M2*Pesos!$B$12+N2*Pesos!$B$13+O2*Pesos!$B$14+P2*Pesos!$B$15+Q2*Pesos!$B$16+R2*Pesos!$B$17+S2*Pesos!$B$18+T2*Pesos!$B$19+U2*Pesos!$B$20+V2*Pesos!$B$21 -> 5740 | X2: =Espíritus!C35 -> 4826 | Y2: =W2+X2 -> 10566 | Z2: =IF($Y$16=0,0,Y2/$Y$16-1) -> -0.05344845 | AA2: =COUNTIFS('Por foco'!$A$2:$A$579,$A2,'Por foco'!$AA$2:$AA$579,"?*") -> 4
A3: ASC | B3: =COUNTIF('Por foco'!$A$2:$A$579,$A3) -> 69 | C3: =SUMIFS('Por foco'!$E$2:$E$579,'Por foco'!$A$2:$A$579,$A3) -> 4466 | D3: =SUMIFS('Por foco'!$F$2:$F$579,'Por foco'!$A$2:$A$579,$A3) -> 1270 | E3: =SUMIFS('Por foco'!$G$2:$G$579,'Por foco'!$A$2:$A$579,$A3) -> 5 | F3: =SUMIFS('Por foco'!$H$2:$H$579,'Por foco'!$A$2:$A$579,$A3) -> 15 | G3: =SUMIFS('Por foco'!$I$2:$I$579,'Por foco'!$A$2:$A$579,$A3) -> 100000 | H3: =SUMIFS('Por foco'!$J$2:$J$579,'Por foco'!$A$2:$A$579,$A3) -> 75 | I3: =SUMIFS('Por foco'!$K$2:$K$579,'Por foco'!$A$2:$A$579,$A3) -> 0 | J3: =SUMIFS('Por foco'!$L$2:$L$579,'Por foco'!$A$2:$A$579,$A3) -> 0 | K3: =SUMIFS('Por foco'!$M$2:$M$579,'Por foco'!$A$2:$A$579,$A3) -> 5 | L3: =SUMIFS('Por foco'!$N$2:$N$579,'Por foco'!$A$2:$A$579,$A3) -> 12 | M3: =SUMIFS('Por foco'!$O$2:$O$579,'Por foco'!$A$2:$A$579,$A3) -> 11 | N3: =SUMIFS('Por foco'!$P$2:$P$579,'Por foco'!$A$2:$A$579,$A3) -> 6 | O3: =SUMIFS('Por foco'!$Q$2:$Q$579,'Por foco'!$A$2:$A$579,$A3) -> 7 | P3: =SUMIFS('Por foco'!$R$2:$R$579,'Por foco'!$A$2:$A$579,$A3) -> 1 | Q3: =SUMIFS('Por foco'!$S$2:$S$579,'Por foco'!$A$2:$A$579,$A3) -> 0 | R3: =SUMIFS('Por foco'!$T$2:$T$579,'Por foco'!$A$2:$A$579,$A3) -> 0 | S3: =SUMIFS('Por foco'!$U$2:$U$579,'Por foco'!$A$2:$A$579,$A3) -> 0 | T3: =SUMIFS('Por foco'!$V$2:$V$579,'Por foco'!$A$2:$A$579,$A3) -> 100 | U3: =SUMIFS('Por foco'!$W$2:$W$579,'Por foco'!$A$2:$A$579,$A3) -> 8 | V3: =SUMIFS('Por foco'!$X$2:$X$579,'Por foco'!$A$2:$A$579,$A3) -> 19 | W3: =C3*Pesos!$B$2+D3*Pesos!$B$3+E3*Pesos!$B$4+F3*Pesos!$B$5+G3*Pesos!$B$6+H3*Pesos!$B$7+I3*Pesos!$B$8+J3*Pesos!$B$9+K3*Pesos!$B$10+L3*Pesos!$B$11+M3*Pesos!$B$12+N3*Pesos!$B$13+O3*Pesos!$B$14+P3*Pesos!$B$15+Q3*Pesos!$B$16+R3*Pesos!$B$17+S3*Pesos!$B$18+T3*Pesos!$B$19+U3*Pesos!$B$20+V3*Pesos!$B$21 -> 5740 | X3: =Espíritus!D35 -> 5590.5 | Y3: =W3+X3 -> 11330.5 | Z3: =IF($Y$16=0,0,Y3/$Y$16-1) -> 0.015039025 | AA3: =COUNTIFS('Por foco'!$A$2:$A$579,$A3,'Por foco'!$AA$2:$AA$579,"?*") -> 4
A4: FCU | B4: =COUNTIF('Por foco'!$A$2:$A$579,$A4) -> 67 | C4: =SUMIFS('Por foco'!$E$2:$E$579,'Por foco'!$A$2:$A$579,$A4) -> 4221 | D4: =SUMIFS('Por foco'!$F$2:$F$579,'Por foco'!$A$2:$A$579,$A4) -> 1570 | E4: =SUMIFS('Por foco'!$G$2:$G$579,'Por foco'!$A$2:$A$579,$A4) -> 15 | F4: =SUMIFS('Por foco'!$H$2:$H$579,'Por foco'!$A$2:$A$579,$A4) -> 15 | G4: =SUMIFS('Por foco'!$I$2:$I$579,'Por foco'!$A$2:$A$579,$A4) -> 100000 | H4: =SUMIFS('Por foco'!$J$2:$J$579,'Por foco'!$A$2:$A$579,$A4) -> 75 | I4: =SUMIFS('Por foco'!$K$2:$K$579,'Por foco'!$A$2:$A$579,$A4) -> 50 | J4: =SUMIFS('Por foco'!$L$2:$L$579,'Por foco'!$A$2:$A$579,$A4) -> 0 | K4: =SUMIFS('Por foco'!$M$2:$M$579,'Por foco'!$A$2:$A$579,$A4) -> 2 | L4: =SUMIFS('Por foco'!$N$2:$N$579,'Por foco'!$A$2:$A$579,$A4) -> 10 | M4: =SUMIFS('Por foco'!$O$2:$O$579,'Por foco'!$A$2:$A$579,$A4) -> 16 | N4: =SUMIFS('Por foco'!$P$2:$P$579,'Por foco'!$A$2:$A$579,$A4) -> 8 | O4: =SUMIFS('Por foco'!$Q$2:$Q$579,'Por foco'!$A$2:$A$579,$A4) -> 9 | P4: =SUMIFS('Por foco'!$R$2:$R$579,'Por foco'!$A$2:$A$579,$A4) -> 4 | Q4: =SUMIFS('Por foco'!$S$2:$S$579,'Por foco'!$A$2:$A$579,$A4) -> 0 | R4: =SUMIFS('Por foco'!$T$2:$T$579,'Por foco'!$A$2:$A$579,$A4) -> 0 | S4: =SUMIFS('Por foco'!$U$2:$U$579,'Por foco'!$A$2:$A$579,$A4) -> 0 | T4: =SUMIFS('Por foco'!$V$2:$V$579,'Por foco'!$A$2:$A$579,$A4) -> 120 | U4: =SUMIFS('Por foco'!$W$2:$W$579,'Por foco'!$A$2:$A$579,$A4) -> 7 | V4: =SUMIFS('Por foco'!$X$2:$X$579,'Por foco'!$A$2:$A$579,$A4) -> 23 | W4: =C4*Pesos!$B$2+D4*Pesos!$B$3+E4*Pesos!$B$4+F4*Pesos!$B$5+G4*Pesos!$B$6+H4*Pesos!$B$7+I4*Pesos!$B$8+J4*Pesos!$B$9+K4*Pesos!$B$10+L4*Pesos!$B$11+M4*Pesos!$B$12+N4*Pesos!$B$13+O4*Pesos!$B$14+P4*Pesos!$B$15+Q4*Pesos!$B$16+R4*Pesos!$B$17+S4*Pesos!$B$18+T4*Pesos!$B$19+U4*Pesos!$B$20+V4*Pesos!$B$21 -> 6055 | X4: =Espíritus!E35 -> 4468.5 | Y4: =W4+X4 -> 10523.5 | Z4: =IF($Y$16=0,0,Y4/$Y$16-1) -> -0.057255798 | AA4: =COUNTIFS('Por foco'!$A$2:$A$579,$A4,'Por foco'!$AA$2:$AA$579,"?*") -> 6
A5: HSN | B5: =COUNTIF('Por foco'!$A$2:$A$579,$A5) -> 64 | C5: =SUMIFS('Por foco'!$E$2:$E$579,'Por foco'!$A$2:$A$579,$A5) -> 4137 | D5: =SUMIFS('Por foco'!$F$2:$F$579,'Por foco'!$A$2:$A$579,$A5) -> 1720 | E5: =SUMIFS('Por foco'!$G$2:$G$579,'Por foco'!$A$2:$A$579,$A5) -> 5 | F5: =SUMIFS('Por foco'!$H$2:$H$579,'Por foco'!$A$2:$A$579,$A5) -> 15 | G5: =SUMIFS('Por foco'!$I$2:$I$579,'Por foco'!$A$2:$A$579,$A5) -> 75000 | H5: =SUMIFS('Por foco'!$J$2:$J$579,'Por foco'!$A$2:$A$579,$A5) -> 150 | I5: =SUMIFS('Por foco'!$K$2:$K$579,'Por foco'!$A$2:$A$579,$A5) -> 255 | J5: =SUMIFS('Por foco'!$L$2:$L$579,'Por foco'!$A$2:$A$579,$A5) -> 0 | K5: =SUMIFS('Por foco'!$M$2:$M$579,'Por foco'!$A$2:$A$579,$A5) -> 2 | L5: =SUMIFS('Por foco'!$N$2:$N$579,'Por foco'!$A$2:$A$579,$A5) -> 7 | M5: =SUMIFS('Por foco'!$O$2:$O$579,'Por foco'!$A$2:$A$579,$A5) -> 9 | N5: =SUMIFS('Por foco'!$P$2:$P$579,'Por foco'!$A$2:$A$579,$A5) -> 3 | O5: =SUMIFS('Por foco'!$Q$2:$Q$579,'Por foco'!$A$2:$A$579,$A5) -> 21 | P5: =SUMIFS('Por foco'!$R$2:$R$579,'Por foco'!$A$2:$A$579,$A5) -> 7 | Q5: =SUMIFS('Por foco'!$S$2:$S$579,'Por foco'!$A$2:$A$579,$A5) -> 3 | R5: =SUMIFS('Por foco'!$T$2:$T$579,'Por foco'!$A$2:$A$579,$A5) -> 0 | S5: =SUMIFS('Por foco'!$U$2:$U$579,'Por foco'!$A$2:$A$579,$A5) -> 0 | T5: =SUMIFS('Por foco'!$V$2:$V$579,'Por foco'!$A$2:$A$579,$A5) -> 80 | U5: =SUMIFS('Por foco'!$W$2:$W$579,'Por foco'!$A$2:$A$579,$A5) -> 12 | V5: =SUMIFS('Por foco'!$X$2:$X$579,'Por foco'!$A$2:$A$579,$A5) -> 16 | W5: =C5*Pesos!$B$2+D5*Pesos!$B$3+E5*Pesos!$B$4+F5*Pesos!$B$5+G5*Pesos!$B$6+H5*Pesos!$B$7+I5*Pesos!$B$8+J5*Pesos!$B$9+K5*Pesos!$B$10+L5*Pesos!$B$11+M5*Pesos!$B$12+N5*Pesos!$B$13+O5*Pesos!$B$14+P5*Pesos!$B$15+Q5*Pesos!$B$16+R5*Pesos!$B$17+S5*Pesos!$B$18+T5*Pesos!$B$19+U5*Pesos!$B$20+V5*Pesos!$B$21 -> 6035 | X5: =Espíritus!F35 -> 3207.5 | Y5: =W5+X5 -> 9242.5 | Z5: =IF($Y$16=0,0,Y5/$Y$16-1) -> -0.17201375 | AA5: =COUNTIFS('Por foco'!$A$2:$A$579,$A5,'Por foco'!$AA$2:$AA$579,"?*") -> 4
A6: NAS | B6: =COUNTIF('Por foco'!$A$2:$A$579,$A6) -> 68 | C6: =SUMIFS('Por foco'!$E$2:$E$579,'Por foco'!$A$2:$A$579,$A6) -> 4417 | D6: =SUMIFS('Por foco'!$F$2:$F$579,'Por foco'!$A$2:$A$579,$A6) -> 1170 | E6: =SUMIFS('Por foco'!$G$2:$G$579,'Por foco'!$A$2:$A$579,$A6) -> 38 | F6: =SUMIFS('Por foco'!$H$2:$H$579,'Por foco'!$A$2:$A$579,$A6) -> 25 | G6: =SUMIFS('Por foco'!$I$2:$I$579,'Por foco'!$A$2:$A$579,$A6) -> 80000 | H6: =SUMIFS('Por foco'!$J$2:$J$579,'Por foco'!$A$2:$A$579,$A6) -> 325 | I6: =SUMIFS('Por foco'!$K$2:$K$579,'Por foco'!$A$2:$A$579,$A6) -> 25 | J6: =SUMIFS('Por foco'!$L$2:$L$579,'Por foco'!$A$2:$A$579,$A6) -> 50 | K6: =SUMIFS('Por foco'!$M$2:$M$579,'Por foco'!$A$2:$A$579,$A6) -> 4 | L6: =SUMIFS('Por foco'!$N$2:$N$579,'Por foco'!$A$2:$A$579,$A6) -> 16 | M6: =SUMIFS('Por foco'!$O$2:$O$579,'Por foco'!$A$2:$A$579,$A6) -> 16 | N6: =SUMIFS('Por foco'!$P$2:$P$579,'Por foco'!$A$2:$A$579,$A6) -> 2 | O6: =SUMIFS('Por foco'!$Q$2:$Q$579,'Por foco'!$A$2:$A$579,$A6) -> 4 | P6: =SUMIFS('Por foco'!$R$2:$R$579,'Por foco'!$A$2:$A$579,$A6) -> 2 | Q6: =SUMIFS('Por foco'!$S$2:$S$579,'Por foco'!$A$2:$A$579,$A6) -> 5 | R6: =SUMIFS('Por foco'!$T$2:$T$579,'Por foco'!$A$2:$A$579,$A6) -> 0 | S6: =SUMIFS('Por foco'!$U$2:$U$579,'Por foco'!$A$2:$A$579,$A6) -> 0 | T6: =SUMIFS('Por foco'!$V$2:$V$579,'Por foco'!$A$2:$A$579,$A6) -> 300 | U6: =SUMIFS('Por foco'!$W$2:$W$579,'Por foco'!$A$2:$A$579,$A6) -> 22 | V6: =SUMIFS('Por foco'!$X$2:$X$579,'Por foco'!$A$2:$A$579,$A6) -> 20 | W6: =C6*Pesos!$B$2+D6*Pesos!$B$3+E6*Pesos!$B$4+F6*Pesos!$B$5+G6*Pesos!$B$6+H6*Pesos!$B$7+I6*Pesos!$B$8+J6*Pesos!$B$9+K6*Pesos!$B$10+L6*Pesos!$B$11+M6*Pesos!$B$12+N6*Pesos!$B$13+O6*Pesos!$B$14+P6*Pesos!$B$15+Q6*Pesos!$B$16+R6*Pesos!$B$17+S6*Pesos!$B$18+T6*Pesos!$B$19+U6*Pesos!$B$20+V6*Pesos!$B$21 -> 6580 | X6: =Espíritus!G35 -> 5172.5 | Y6: =W6+X6 -> 11752.5 | Z6: =IF($Y$16=0,0,Y6/$Y$16-1) -> 0.052843753 | AA6: =COUNTIFS('Por foco'!$A$2:$A$579,$A6,'Por foco'!$AA$2:$AA$579,"?*") -> 4
A7: SHD | B7: =COUNTIF('Por foco'!$A$2:$A$579,$A7) -> 65 | C7: =SUMIFS('Por foco'!$E$2:$E$579,'Por foco'!$A$2:$A$579,$A7) -> 4123 | D7: =SUMIFS('Por foco'!$F$2:$F$579,'Por foco'!$A$2:$A$579,$A7) -> 1120 | E7: =SUMIFS('Por foco'!$G$2:$G$579,'Por foco'!$A$2:$A$579,$A7) -> 18 | F7: =SUMIFS('Por foco'!$H$2:$H$579,'Por foco'!$A$2:$A$579,$A7) -> 15 | G7: =SUMIFS('Por foco'!$I$2:$I$579,'Por foco'!$A$2:$A$579,$A7) -> 300000 | H7: =SUMIFS('Por foco'!$J$2:$J$579,'Por foco'!$A$2:$A$579,$A7) -> 375 | I7: =SUMIFS('Por foco'!$K$2:$K$579,'Por foco'!$A$2:$A$579,$A7) -> 25 | J7: =SUMIFS('Por foco'!$L$2:$L$579,'Por foco'!$A$2:$A$579,$A7) -> 50 | K7: =SUMIFS('Por foco'!$M$2:$M$579,'Por foco'!$A$2:$A$579,$A7) -> 4 | L7: =SUMIFS('Por foco'!$N$2:$N$579,'Por foco'!$A$2:$A$579,$A7) -> 20 | M7: =SUMIFS('Por foco'!$O$2:$O$579,'Por foco'!$A$2:$A$579,$A7) -> 17 | N7: =SUMIFS('Por foco'!$P$2:$P$579,'Por foco'!$A$2:$A$579,$A7) -> 4 | O7: =SUMIFS('Por foco'!$Q$2:$Q$579,'Por foco'!$A$2:$A$579,$A7) -> 4 | P7: =SUMIFS('Por foco'!$R$2:$R$579,'Por foco'!$A$2:$A$579,$A7) -> 5 | Q7: =SUMIFS('Por foco'!$S$2:$S$579,'Por foco'!$A$2:$A$579,$A7) -> 2 | R7: =SUMIFS('Por foco'!$T$2:$T$579,'Por foco'!$A$2:$A$579,$A7) -> 0 | S7: =SUMIFS('Por foco'!$U$2:$U$579,'Por foco'!$A$2:$A$579,$A7) -> 0 | T7: =SUMIFS('Por foco'!$V$2:$V$579,'Por foco'!$A$2:$A$579,$A7) -> 100 | U7: =SUMIFS('Por foco'!$W$2:$W$579,'Por foco'!$A$2:$A$579,$A7) -> 10 | V7: =SUMIFS('Por foco'!$X$2:$X$579,'Por foco'!$A$2:$A$579,$A7) -> 18 | W7: =C7*Pesos!$B$2+D7*Pesos!$B$3+E7*Pesos!$B$4+F7*Pesos!$B$5+G7*Pesos!$B$6+H7*Pesos!$B$7+I7*Pesos!$B$8+J7*Pesos!$B$9+K7*Pesos!$B$10+L7*Pesos!$B$11+M7*Pesos!$B$12+N7*Pesos!$B$13+O7*Pesos!$B$14+P7*Pesos!$B$15+Q7*Pesos!$B$16+R7*Pesos!$B$17+S7*Pesos!$B$18+T7*Pesos!$B$19+U7*Pesos!$B$20+V7*Pesos!$B$21 -> 6775 | X7: =Espíritus!H35 -> 4694.5 | Y7: =W7+X7 -> 11469.5 | Z7: =IF($Y$16=0,0,Y7/$Y$16-1) -> 0.027491293 | AA7: =COUNTIFS('Por foco'!$A$2:$A$579,$A7,'Por foco'!$AA$2:$AA$579,"?*") -> 4
A8: APF | B8: =COUNTIF('Por foco'!$A$2:$A$579,$A8) -> 62 | C8: =SUMIFS('Por foco'!$E$2:$E$579,'Por foco'!$A$2:$A$579,$A8) -> 4025 | D8: =SUMIFS('Por foco'!$F$2:$F$579,'Por foco'!$A$2:$A$579,$A8) -> 1070 | E8: =SUMIFS('Por foco'!$G$2:$G$579,'Por foco'!$A$2:$A$579,$A8) -> 18 | F8: =SUMIFS('Por foco'!$H$2:$H$579,'Por foco'!$A$2:$A$579,$A8) -> 25 | G8: =SUMIFS('Por foco'!$I$2:$I$579,'Por foco'!$A$2:$A$579,$A8) -> 320000 | H8: =SUMIFS('Por foco'!$J$2:$J$579,'Por foco'!$A$2:$A$579,$A8) -> 425 | I8: =SUMIFS('Por foco'!$K$2:$K$579,'Por foco'!$A$2:$A$579,$A8) -> 25 | J8: =SUMIFS('Por foco'!$L$2:$L$579,'Por foco'!$A$2:$A$579,$A8) -> 50 | K8: =SUMIFS('Por foco'!$M$2:$M$579,'Por foco'!$A$2:$A$579,$A8) -> 3 | L8: =SUMIFS('Por foco'!$N$2:$N$579,'Por foco'!$A$2:$A$579,$A8) -> 21 | M8: =SUMIFS('Por foco'!$O$2:$O$579,'Por foco'!$A$2:$A$579,$A8) -> 19 | N8: =SUMIFS('Por foco'!$P$2:$P$579,'Por foco'!$A$2:$A$579,$A8) -> 2 | O8: =SUMIFS('Por foco'!$Q$2:$Q$579,'Por foco'!$A$2:$A$579,$A8) -> 5 | P8: =SUMIFS('Por foco'!$R$2:$R$579,'Por foco'!$A$2:$A$579,$A8) -> 4 | Q8: =SUMIFS('Por foco'!$S$2:$S$579,'Por foco'!$A$2:$A$579,$A8) -> 3 | R8: =SUMIFS('Por foco'!$T$2:$T$579,'Por foco'!$A$2:$A$579,$A8) -> 0 | S8: =SUMIFS('Por foco'!$U$2:$U$579,'Por foco'!$A$2:$A$579,$A8) -> 0 | T8: =SUMIFS('Por foco'!$V$2:$V$579,'Por foco'!$A$2:$A$579,$A8) -> 100 | U8: =SUMIFS('Por foco'!$W$2:$W$579,'Por foco'!$A$2:$A$579,$A8) -> 15 | V8: =SUMIFS('Por foco'!$X$2:$X$579,'Por foco'!$A$2:$A$579,$A8) -> 20 | W8: =C8*Pesos!$B$2+D8*Pesos!$B$3+E8*Pesos!$B$4+F8*Pesos!$B$5+G8*Pesos!$B$6+H8*Pesos!$B$7+I8*Pesos!$B$8+J8*Pesos!$B$9+K8*Pesos!$B$10+L8*Pesos!$B$11+M8*Pesos!$B$12+N8*Pesos!$B$13+O8*Pesos!$B$14+P8*Pesos!$B$15+Q8*Pesos!$B$16+R8*Pesos!$B$17+S8*Pesos!$B$18+T8*Pesos!$B$19+U8*Pesos!$B$20+V8*Pesos!$B$21 -> 6815 | X8: =Espíritus!I35 -> 5479.5 | Y8: =W8+X8 -> 12294.5 | Z8: =IF($Y$16=0,0,Y8/$Y$16-1) -> 0.10139864 | AA8: =COUNTIFS('Por foco'!$A$2:$A$579,$A8,'Por foco'!$AA$2:$AA$579,"?*") -> 4
A9: NRE | B9: =COUNTIF('Por foco'!$A$2:$A$579,$A9) -> 67 | C9: =SUMIFS('Por foco'!$E$2:$E$579,'Por foco'!$A$2:$A$579,$A9) -> 4606 | D9: =SUMIFS('Por foco'!$F$2:$F$579,'Por foco'!$A$2:$A$579,$A9) -> 1070 | E9: =SUMIFS('Por foco'!$G$2:$G$579,'Por foco'!$A$2:$A$579,$A9) -> 19 | F9: =SUMIFS('Por foco'!$H$2:$H$579,'Por foco'!$A$2:$A$579,$A9) -> 20 | G9: =SUMIFS('Por foco'!$I$2:$I$579,'Por foco'!$A$2:$A$579,$A9) -> 500000 | H9: =SUMIFS('Por foco'!$J$2:$J$579,'Por foco'!$A$2:$A$579,$A9) -> 225 | I9: =SUMIFS('Por foco'!$K$2:$K$579,'Por foco'!$A$2:$A$579,$A9) -> 25 | J9: =SUMIFS('Por foco'!$L$2:$L$579,'Por foco'!$A$2:$A$579,$A9) -> 75 | K9: =SUMIFS('Por foco'!$M$2:$M$579,'Por foco'!$A$2:$A$579,$A9) -> 3 | L9: =SUMIFS('Por foco'!$N$2:$N$579,'Por foco'!$A$2:$A$579,$A9) -> 15 | M9: =SUMIFS('Por foco'!$O$2:$O$579,'Por foco'!$A$2:$A$579,$A9) -> 11 | N9: =SUMIFS('Por foco'!$P$2:$P$579,'Por foco'!$A$2:$A$579,$A9) -> 8 | O9: =SUMIFS('Por foco'!$Q$2:$Q$579,'Por foco'!$A$2:$A$579,$A9) -> 4 | P9: =SUMIFS('Por foco'!$R$2:$R$579,'Por foco'!$A$2:$A$579,$A9) -> 6 | Q9: =SUMIFS('Por foco'!$S$2:$S$579,'Por foco'!$A$2:$A$579,$A9) -> 2 | R9: =SUMIFS('Por foco'!$T$2:$T$579,'Por foco'!$A$2:$A$579,$A9) -> 0 | S9: =SUMIFS('Por foco'!$U$2:$U$579,'Por foco'!$A$2:$A$579,$A9) -> 0 | T9: =SUMIFS('Por foco'!$V$2:$V$579,'Por foco'!$A$2:$A$579,$A9) -> 100 | U9: =SUMIFS('Por foco'!$W$2:$W$579,'Por foco'!$A$2:$A$579,$A9) -> 12 | V9: =SUMIFS('Por foco'!$X$2:$X$579,'Por foco'!$A$2:$A$579,$A9) -> 24 | W9: =C9*Pesos!$B$2+D9*Pesos!$B$3+E9*Pesos!$B$4+F9*Pesos!$B$5+G9*Pesos!$B$6+H9*Pesos!$B$7+I9*Pesos!$B$8+J9*Pesos!$B$9+K9*Pesos!$B$10+L9*Pesos!$B$11+M9*Pesos!$B$12+N9*Pesos!$B$13+O9*Pesos!$B$14+P9*Pesos!$B$15+Q9*Pesos!$B$16+R9*Pesos!$B$17+S9*Pesos!$B$18+T9*Pesos!$B$19+U9*Pesos!$B$20+V9*Pesos!$B$21 -> 6400 | X9: =Espíritus!J35 -> 5722 | Y9: =W9+X9 -> 12122 | Z9: =IF($Y$16=0,0,Y9/$Y$16-1) -> 0.085945286 | AA9: =COUNTIFS('Por foco'!$A$2:$A$579,$A9,'Por foco'!$AA$2:$AA$579,"?*") -> 4
A10: ZWB | B10: =COUNTIF('Por foco'!$A$2:$A$579,$A10) -> 7 | C10: =SUMIFS('Por foco'!$E$2:$E$579,'Por foco'!$A$2:$A$579,$A10) -> 245 | D10: =SUMIFS('Por foco'!$F$2:$F$579,'Por foco'!$A$2:$A$579,$A10) -> 0 | E10: =SUMIFS('Por foco'!$G$2:$G$579,'Por foco'!$A$2:$A$579,$A10) -> 0 | F10: =SUMIFS('Por foco'!$H$2:$H$579,'Por foco'!$A$2:$A$579,$A10) -> 0 | G10: =SUMIFS('Por foco'!$I$2:$I$579,'Por foco'!$A$2:$A$579,$A10) -> 60000 | H10: =SUMIFS('Por foco'!$J$2:$J$579,'Por foco'!$A$2:$A$579,$A10) -> 0 | I10: =SUMIFS('Por foco'!$K$2:$K$579,'Por foco'!$A$2:$A$579,$A10) -> 0 | J10: =SUMIFS('Por foco'!$L$2:$L$579,'Por foco'!$A$2:$A$579,$A10) -> 0 | K10: =SUMIFS('Por foco'!$M$2:$M$579,'Por foco'!$A$2:$A$579,$A10) -> 0 | L10: =SUMIFS('Por foco'!$N$2:$N$579,'Por foco'!$A$2:$A$579,$A10) -> 0 | M10: =SUMIFS('Por foco'!$O$2:$O$579,'Por foco'!$A$2:$A$579,$A10) -> 0 | N10: =SUMIFS('Por foco'!$P$2:$P$579,'Por foco'!$A$2:$A$579,$A10) -> 0 | O10: =SUMIFS('Por foco'!$Q$2:$Q$579,'Por foco'!$A$2:$A$579,$A10) -> 0 | P10: =SUMIFS('Por foco'!$R$2:$R$579,'Por foco'!$A$2:$A$579,$A10) -> 0 | Q10: =SUMIFS('Por foco'!$S$2:$S$579,'Por foco'!$A$2:$A$579,$A10) -> 0 | R10: =SUMIFS('Por foco'!$T$2:$T$579,'Por foco'!$A$2:$A$579,$A10) -> 3500 | S10: =SUMIFS('Por foco'!$U$2:$U$579,'Por foco'!$A$2:$A$579,$A10) -> 0 | T10: =SUMIFS('Por foco'!$V$2:$V$579,'Por foco'!$A$2:$A$579,$A10) -> 0 | U10: =SUMIFS('Por foco'!$W$2:$W$579,'Por foco'!$A$2:$A$579,$A10) -> 0 | V10: =SUMIFS('Por foco'!$X$2:$X$579,'Por foco'!$A$2:$A$579,$A10) -> 7 | W10: =C10*Pesos!$B$2+D10*Pesos!$B$3+E10*Pesos!$B$4+F10*Pesos!$B$5+G10*Pesos!$B$6+H10*Pesos!$B$7+I10*Pesos!$B$8+J10*Pesos!$B$9+K10*Pesos!$B$10+L10*Pesos!$B$11+M10*Pesos!$B$12+N10*Pesos!$B$13+O10*Pesos!$B$14+P10*Pesos!$B$15+Q10*Pesos!$B$16+R10*Pesos!$B$17+S10*Pesos!$B$18+T10*Pesos!$B$19+U10*Pesos!$B$20+V10*Pesos!$B$21 -> 190 | X10: =Espíritus!K35 -> 2030 | Y10: =W10+X10 -> 2220 | Z10: =IF($Y$16=0,0,Y10/$Y$16-1) -> -0.80112205 | AA10: =COUNTIFS('Por foco'!$A$2:$A$579,$A10,'Por foco'!$AA$2:$AA$579,"?*") -> 0
A11: ZWE | B11: =COUNTIF('Por foco'!$A$2:$A$579,$A11) -> 7 | C11: =SUMIFS('Por foco'!$E$2:$E$579,'Por foco'!$A$2:$A$579,$A11) -> 245 | D11: =SUMIFS('Por foco'!$F$2:$F$579,'Por foco'!$A$2:$A$579,$A11) -> 0 | E11: =SUMIFS('Por foco'!$G$2:$G$579,'Por foco'!$A$2:$A$579,$A11) -> 0 | F11: =SUMIFS('Por foco'!$H$2:$H$579,'Por foco'!$A$2:$A$579,$A11) -> 0 | G11: =SUMIFS('Por foco'!$I$2:$I$579,'Por foco'!$A$2:$A$579,$A11) -> 1340000 | H11: =SUMIFS('Por foco'!$J$2:$J$579,'Por foco'!$A$2:$A$579,$A11) -> 0 | I11: =SUMIFS('Por foco'!$K$2:$K$579,'Por foco'!$A$2:$A$579,$A11) -> 0 | J11: =SUMIFS('Por foco'!$L$2:$L$579,'Por foco'!$A$2:$A$579,$A11) -> 0 | K11: =SUMIFS('Por foco'!$M$2:$M$579,'Por foco'!$A$2:$A$579,$A11) -> 0 | L11: =SUMIFS('Por foco'!$N$2:$N$579,'Por foco'!$A$2:$A$579,$A11) -> 0 | M11: =SUMIFS('Por foco'!$O$2:$O$579,'Por foco'!$A$2:$A$579,$A11) -> 0 | N11: =SUMIFS('Por foco'!$P$2:$P$579,'Por foco'!$A$2:$A$579,$A11) -> 0 | O11: =SUMIFS('Por foco'!$Q$2:$Q$579,'Por foco'!$A$2:$A$579,$A11) -> 0 | P11: =SUMIFS('Por foco'!$R$2:$R$579,'Por foco'!$A$2:$A$579,$A11) -> 0 | Q11: =SUMIFS('Por foco'!$S$2:$S$579,'Por foco'!$A$2:$A$579,$A11) -> 0 | R11: =SUMIFS('Por foco'!$T$2:$T$579,'Por foco'!$A$2:$A$579,$A11) -> 30150 | S11: =SUMIFS('Por foco'!$U$2:$U$579,'Por foco'!$A$2:$A$579,$A11) -> 6 | T11: =SUMIFS('Por foco'!$V$2:$V$579,'Por foco'!$A$2:$A$579,$A11) -> 0 | U11: =SUMIFS('Por foco'!$W$2:$W$579,'Por foco'!$A$2:$A$579,$A11) -> 2 | V11: =SUMIFS('Por foco'!$X$2:$X$579,'Por foco'!$A$2:$A$579,$A11) -> 7 | W11: =C11*Pesos!$B$2+D11*Pesos!$B$3+E11*Pesos!$B$4+F11*Pesos!$B$5+G11*Pesos!$B$6+H11*Pesos!$B$7+I11*Pesos!$B$8+J11*Pesos!$B$9+K11*Pesos!$B$10+L11*Pesos!$B$11+M11*Pesos!$B$12+N11*Pesos!$B$13+O11*Pesos!$B$14+P11*Pesos!$B$15+Q11*Pesos!$B$16+R11*Pesos!$B$17+S11*Pesos!$B$18+T11*Pesos!$B$19+U11*Pesos!$B$20+V11*Pesos!$B$21 -> 3563 | X11: =Espíritus!L35 -> 3673 | Y11: =W11+X11 -> 7236 | Z11: =IF($Y$16=0,0,Y11/$Y$16-1) -> -0.35176538 | AA11: =COUNTIFS('Por foco'!$A$2:$A$579,$A11,'Por foco'!$AA$2:$AA$579,"?*") -> 0
A12: ZWI | B12: =COUNTIF('Por foco'!$A$2:$A$579,$A12) -> 7 | C12: =SUMIFS('Por foco'!$E$2:$E$579,'Por foco'!$A$2:$A$579,$A12) -> 245 | D12: =SUMIFS('Por foco'!$F$2:$F$579,'Por foco'!$A$2:$A$579,$A12) -> 0 | E12: =SUMIFS('Por foco'!$G$2:$G$579,'Por foco'!$A$2:$A$579,$A12) -> 0 | F12: =SUMIFS('Por foco'!$H$2:$H$579,'Por foco'!$A$2:$A$579,$A12) -> 0 | G12: =SUMIFS('Por foco'!$I$2:$I$579,'Por foco'!$A$2:$A$579,$A12) -> 1840000 | H12: =SUMIFS('Por foco'!$J$2:$J$579,'Por foco'!$A$2:$A$579,$A12) -> 0 | I12: =SUMIFS('Por foco'!$K$2:$K$579,'Por foco'!$A$2:$A$579,$A12) -> 0 | J12: =SUMIFS('Por foco'!$L$2:$L$579,'Por foco'!$A$2:$A$579,$A12) -> 0 | K12: =SUMIFS('Por foco'!$M$2:$M$579,'Por foco'!$A$2:$A$579,$A12) -> 0 | L12: =SUMIFS('Por foco'!$N$2:$N$579,'Por foco'!$A$2:$A$579,$A12) -> 0 | M12: =SUMIFS('Por foco'!$O$2:$O$579,'Por foco'!$A$2:$A$579,$A12) -> 0 | N12: =SUMIFS('Por foco'!$P$2:$P$579,'Por foco'!$A$2:$A$579,$A12) -> 0 | O12: =SUMIFS('Por foco'!$Q$2:$Q$579,'Por foco'!$A$2:$A$579,$A12) -> 0 | P12: =SUMIFS('Por foco'!$R$2:$R$579,'Por foco'!$A$2:$A$579,$A12) -> 0 | Q12: =SUMIFS('Por foco'!$S$2:$S$579,'Por foco'!$A$2:$A$579,$A12) -> 0 | R12: =SUMIFS('Por foco'!$T$2:$T$579,'Por foco'!$A$2:$A$579,$A12) -> 32150 | S12: =SUMIFS('Por foco'!$U$2:$U$579,'Por foco'!$A$2:$A$579,$A12) -> 8 | T12: =SUMIFS('Por foco'!$V$2:$V$579,'Por foco'!$A$2:$A$579,$A12) -> 0 | U12: =SUMIFS('Por foco'!$W$2:$W$579,'Por foco'!$A$2:$A$579,$A12) -> 0 | V12: =SUMIFS('Por foco'!$X$2:$X$579,'Por foco'!$A$2:$A$579,$A12) -> 7 | W12: =C12*Pesos!$B$2+D12*Pesos!$B$3+E12*Pesos!$B$4+F12*Pesos!$B$5+G12*Pesos!$B$6+H12*Pesos!$B$7+I12*Pesos!$B$8+J12*Pesos!$B$9+K12*Pesos!$B$10+L12*Pesos!$B$11+M12*Pesos!$B$12+N12*Pesos!$B$13+O12*Pesos!$B$14+P12*Pesos!$B$15+Q12*Pesos!$B$16+R12*Pesos!$B$17+S12*Pesos!$B$18+T12*Pesos!$B$19+U12*Pesos!$B$20+V12*Pesos!$B$21 -> 4643 | X12: =Espíritus!M35 -> 3985 | Y12: =W12+X12 -> 8628 | Z12: =IF($Y$16=0,0,Y12/$Y$16-1) -> -0.22706353 | AA12: =COUNTIFS('Por foco'!$A$2:$A$579,$A12,'Por foco'!$AA$2:$AA$579,"?*") -> 0
A13: ZWM | B13: =COUNTIF('Por foco'!$A$2:$A$579,$A13) -> 7 | C13: =SUMIFS('Por foco'!$E$2:$E$579,'Por foco'!$A$2:$A$579,$A13) -> 245 | D13: =SUMIFS('Por foco'!$F$2:$F$579,'Por foco'!$A$2:$A$579,$A13) -> 0 | E13: =SUMIFS('Por foco'!$G$2:$G$579,'Por foco'!$A$2:$A$579,$A13) -> 0 | F13: =SUMIFS('Por foco'!$H$2:$H$579,'Por foco'!$A$2:$A$579,$A13) -> 0 | G13: =SUMIFS('Por foco'!$I$2:$I$579,'Por foco'!$A$2:$A$579,$A13) -> 1240000 | H13: =SUMIFS('Por foco'!$J$2:$J$579,'Por foco'!$A$2:$A$579,$A13) -> 0 | I13: =SUMIFS('Por foco'!$K$2:$K$579,'Por foco'!$A$2:$A$579,$A13) -> 0 | J13: =SUMIFS('Por foco'!$L$2:$L$579,'Por foco'!$A$2:$A$579,$A13) -> 0 | K13: =SUMIFS('Por foco'!$M$2:$M$579,'Por foco'!$A$2:$A$579,$A13) -> 0 | L13: =SUMIFS('Por foco'!$N$2:$N$579,'Por foco'!$A$2:$A$579,$A13) -> 0 | M13: =SUMIFS('Por foco'!$O$2:$O$579,'Por foco'!$A$2:$A$579,$A13) -> 0 | N13: =SUMIFS('Por foco'!$P$2:$P$579,'Por foco'!$A$2:$A$579,$A13) -> 0 | O13: =SUMIFS('Por foco'!$Q$2:$Q$579,'Por foco'!$A$2:$A$579,$A13) -> 0 | P13: =SUMIFS('Por foco'!$R$2:$R$579,'Por foco'!$A$2:$A$579,$A13) -> 0 | Q13: =SUMIFS('Por foco'!$S$2:$S$579,'Por foco'!$A$2:$A$579,$A13) -> 0 | R13: =SUMIFS('Por foco'!$T$2:$T$579,'Por foco'!$A$2:$A$579,$A13) -> 32150 | S13: =SUMIFS('Por foco'!$U$2:$U$579,'Por foco'!$A$2:$A$579,$A13) -> 8 | T13: =SUMIFS('Por foco'!$V$2:$V$579,'Por foco'!$A$2:$A$579,$A13) -> 0 | U13: =SUMIFS('Por foco'!$W$2:$W$579,'Por foco'!$A$2:$A$579,$A13) -> 0 | V13: =SUMIFS('Por foco'!$X$2:$X$579,'Por foco'!$A$2:$A$579,$A13) -> 7 | W13: =C13*Pesos!$B$2+D13*Pesos!$B$3+E13*Pesos!$B$4+F13*Pesos!$B$5+G13*Pesos!$B$6+H13*Pesos!$B$7+I13*Pesos!$B$8+J13*Pesos!$B$9+K13*Pesos!$B$10+L13*Pesos!$B$11+M13*Pesos!$B$12+N13*Pesos!$B$13+O13*Pesos!$B$14+P13*Pesos!$B$15+Q13*Pesos!$B$16+R13*Pesos!$B$17+S13*Pesos!$B$18+T13*Pesos!$B$19+U13*Pesos!$B$20+V13*Pesos!$B$21 -> 3443 | X13: =Espíritus!N35 -> 3664 | Y13: =W13+X13 -> 7107 | Z13: =IF($Y$16=0,0,Y13/$Y$16-1) -> -0.3633218 | AA13: =COUNTIFS('Por foco'!$A$2:$A$579,$A13,'Por foco'!$AA$2:$AA$579,"?*") -> 0
A14: ZAN | B14: =COUNTIF('Por foco'!$A$2:$A$579,$A14) -> 7 | C14: =SUMIFS('Por foco'!$E$2:$E$579,'Por foco'!$A$2:$A$579,$A14) -> 2548 | D14: =SUMIFS('Por foco'!$F$2:$F$579,'Por foco'!$A$2:$A$579,$A14) -> 400 | E14: =SUMIFS('Por foco'!$G$2:$G$579,'Por foco'!$A$2:$A$579,$A14) -> 10 | F14: =SUMIFS('Por foco'!$H$2:$H$579,'Por foco'!$A$2:$A$579,$A14) -> 10 | G14: =SUMIFS('Por foco'!$I$2:$I$579,'Por foco'!$A$2:$A$579,$A14) -> 1950000 | H14: =SUMIFS('Por foco'!$J$2:$J$579,'Por foco'!$A$2:$A$579,$A14) -> 0 | I14: =SUMIFS('Por foco'!$K$2:$K$579,'Por foco'!$A$2:$A$579,$A14) -> 0 | J14: =SUMIFS('Por foco'!$L$2:$L$579,'Por foco'!$A$2:$A$579,$A14) -> 0 | K14: =SUMIFS('Por foco'!$M$2:$M$579,'Por foco'!$A$2:$A$579,$A14) -> 0 | L14: =SUMIFS('Por foco'!$N$2:$N$579,'Por foco'!$A$2:$A$579,$A14) -> 0 | M14: =SUMIFS('Por foco'!$O$2:$O$579,'Por foco'!$A$2:$A$579,$A14) -> 15 | N14: =SUMIFS('Por foco'!$P$2:$P$579,'Por foco'!$A$2:$A$579,$A14) -> 0 | O14: =SUMIFS('Por foco'!$Q$2:$Q$579,'Por foco'!$A$2:$A$579,$A14) -> 0 | P14: =SUMIFS('Por foco'!$R$2:$R$579,'Por foco'!$A$2:$A$579,$A14) -> 1 | Q14: =SUMIFS('Por foco'!$S$2:$S$579,'Por foco'!$A$2:$A$579,$A14) -> 0 | R14: =SUMIFS('Por foco'!$T$2:$T$579,'Por foco'!$A$2:$A$579,$A14) -> 38910 | S14: =SUMIFS('Por foco'!$U$2:$U$579,'Por foco'!$A$2:$A$579,$A14) -> 10 | T14: =SUMIFS('Por foco'!$V$2:$V$579,'Por foco'!$A$2:$A$579,$A14) -> 0 | U14: =SUMIFS('Por foco'!$W$2:$W$579,'Por foco'!$A$2:$A$579,$A14) -> 9 | V14: =SUMIFS('Por foco'!$X$2:$X$579,'Por foco'!$A$2:$A$579,$A14) -> 3 | W14: =C14*Pesos!$B$2+D14*Pesos!$B$3+E14*Pesos!$B$4+F14*Pesos!$B$5+G14*Pesos!$B$6+H14*Pesos!$B$7+I14*Pesos!$B$8+J14*Pesos!$B$9+K14*Pesos!$B$10+L14*Pesos!$B$11+M14*Pesos!$B$12+N14*Pesos!$B$13+O14*Pesos!$B$14+P14*Pesos!$B$15+Q14*Pesos!$B$16+R14*Pesos!$B$17+S14*Pesos!$B$18+T14*Pesos!$B$19+U14*Pesos!$B$20+V14*Pesos!$B$21 -> 7353.2 | X14: =Espíritus!O35 -> 750 | Y14: =W14+X14 -> 8103.2 | Z14: =IF($Y$16=0,0,Y14/$Y$16-1) -> -0.27407756 | AA14: =COUNTIFS('Por foco'!$A$2:$A$579,$A14,'Por foco'!$AA$2:$AA$579,"?*") -> 0
A15: JUNTA | B15: =COUNTIF('Por foco'!$A$2:$A$579,$A15) -> 11 | C15: =SUMIFS('Por foco'!$E$2:$E$579,'Por foco'!$A$2:$A$579,$A15) -> 420 | D15: =SUMIFS('Por foco'!$F$2:$F$579,'Por foco'!$A$2:$A$579,$A15) -> 0 | E15: =SUMIFS('Por foco'!$G$2:$G$579,'Por foco'!$A$2:$A$579,$A15) -> 0 | F15: =SUMIFS('Por foco'!$H$2:$H$579,'Por foco'!$A$2:$A$579,$A15) -> 0 | G15: =SUMIFS('Por foco'!$I$2:$I$579,'Por foco'!$A$2:$A$579,$A15) -> 800000 | H15: =SUMIFS('Por foco'!$J$2:$J$579,'Por foco'!$A$2:$A$579,$A15) -> 30 | I15: =SUMIFS('Por foco'!$K$2:$K$579,'Por foco'!$A$2:$A$579,$A15) -> 0 | J15: =SUMIFS('Por foco'!$L$2:$L$579,'Por foco'!$A$2:$A$579,$A15) -> 0 | K15: =SUMIFS('Por foco'!$M$2:$M$579,'Por foco'!$A$2:$A$579,$A15) -> 0 | L15: =SUMIFS('Por foco'!$N$2:$N$579,'Por foco'!$A$2:$A$579,$A15) -> 0 | M15: =SUMIFS('Por foco'!$O$2:$O$579,'Por foco'!$A$2:$A$579,$A15) -> 0 | N15: =SUMIFS('Por foco'!$P$2:$P$579,'Por foco'!$A$2:$A$579,$A15) -> 0 | O15: =SUMIFS('Por foco'!$Q$2:$Q$579,'Por foco'!$A$2:$A$579,$A15) -> 0 | P15: =SUMIFS('Por foco'!$R$2:$R$579,'Por foco'!$A$2:$A$579,$A15) -> 0 | Q15: =SUMIFS('Por foco'!$S$2:$S$579,'Por foco'!$A$2:$A$579,$A15) -> 0 | R15: =SUMIFS('Por foco'!$T$2:$T$579,'Por foco'!$A$2:$A$579,$A15) -> 100000 | S15: =SUMIFS('Por foco'!$U$2:$U$579,'Por foco'!$A$2:$A$579,$A15) -> 49 | T15: =SUMIFS('Por foco'!$V$2:$V$579,'Por foco'!$A$2:$A$579,$A15) -> 0 | U15: =SUMIFS('Por foco'!$W$2:$W$579,'Por foco'!$A$2:$A$579,$A15) -> 0 | V15: =SUMIFS('Por foco'!$X$2:$X$579,'Por foco'!$A$2:$A$579,$A15) -> 10 | W15: =C15*Pesos!$B$2+D15*Pesos!$B$3+E15*Pesos!$B$4+F15*Pesos!$B$5+G15*Pesos!$B$6+H15*Pesos!$B$7+I15*Pesos!$B$8+J15*Pesos!$B$9+K15*Pesos!$B$10+L15*Pesos!$B$11+M15*Pesos!$B$12+N15*Pesos!$B$13+O15*Pesos!$B$14+P15*Pesos!$B$15+Q15*Pesos!$B$16+R15*Pesos!$B$17+S15*Pesos!$B$18+T15*Pesos!$B$19+U15*Pesos!$B$20+V15*Pesos!$B$21 -> 5590 | X15: =Espíritus!P35 -> 1335 | Y15: =W15+X15 -> 6925 | Z15: =IF($Y$16=0,0,Y15/$Y$16-1) -> -0.37962621 | AA15: =COUNTIFS('Por foco'!$A$2:$A$579,$A15,'Por foco'!$AA$2:$AA$579,"?*") -> 0
A16: Promedio de las 8 potencias | B16: =AVERAGE(B2:B9) -> 66.5 | C16: =AVERAGE(C2:C9) -> 4310.25 | D16: =AVERAGE(D2:D9) -> 1307.5 | E16: =AVERAGE(E2:E9) -> 14.75 | F16: =AVERAGE(F2:F9) -> 18.125 | G16: =AVERAGE(G2:G9) -> 194375 | H16: =AVERAGE(H2:H9) -> 218.75 | I16: =AVERAGE(I2:I9) -> 50.625 | ... Y16: =AVERAGE(Y2:Y9) -> 11162.625

Sheet Por rama
A1: Árbol | B1: Rama | C1: Focos | D1: Días | E1: Poder político | F1: Estabilidad (%) | G1: Apoyo a la guerra (%) | H1: Mano de obra | I1: Exp. ejército | J1: Exp. naval | K1: Exp. aérea | L1: Casillas de investigación | M1: Bonos de tecnología (usos) | N1: Fábricas civiles | O1: Fábricas militares | P1: Astilleros | Q1: Infraestructura | R1: Otros edificios (niveles) | S1: Equipo (unidades) | T1: Divisiones | U1: Cazas gratis | V1: Reclamos, núcleos y objetivos | W1: Espíritus (agregados)
A2: EFE | B2: dinastia_verde | C2: =COUNTIFS('Por foco'!$A$2:$A$579,$A2,'Por foco'!$B$2:$B$579,$B2) -> 11 | D2: =SUMIFS('Por foco'!$E$2:$E$579,'Por foco'!$A$2:$A$579,$A2,'Por foco'!$B$2:$B$579,$B2) -> 707 | E2: =SUMIFS('Por foco'!$F$2:$F$579,'Por foco'!$A$2:$A$579,$A2,'Por foco'!$B$2:$B$579,$B2) -> 600 | F2: =SUMIFS('Por foco'!$G$2:$G$579,'Por foco'!$A$2:$A$579,$A2,'Por foco'!$B$2:$B$579,$B2) -> 0 | G2: =SUMIFS('Por foco'!$H$2:$H$579,'Por foco'!$A$2:$A$579,$A2,'Por foco'!$B$2:$B$579,$B2) -> 5 | H2: =SUMIFS('Por foco'!$I$2:$I$579,'Por foco'!$A$2:$A$579,$A2,'Por foco'!$B$2:$B$579,$B2) -> 0 | I2: =SUMIFS('Por foco'!$J$2:$J$579,'Por foco'!$A$2:$A$579,$A2,'Por foco'!$B$2:$B$579,$B2) -> 0 | J2: =SUMIFS('Por foco'!$K$2:$K$579,'Por foco'!$A$2:$A$579,$A2,'Por foco'!$B$2:$B$579,$B2) -> 0 | K2: =SUMIFS('Por foco'!$L$2:$L$579,'Por foco'!$A$2:$A$579,$A2,'Por foco'!$B$2:$B$579,$B2) -> 0 | L2: =SUMIFS('Por foco'!$M$2:$M$579,'Por foco'!$A$2:$A$579,$A2,'Por foco'!$B$2:$B$579,$B2) -> 0 | M2: =SUMIFS('Por foco'!$N$2:$N$579,'Por foco'!$A$2:$A$579,$A2,'Por foco'!$B$2:$B$579,$B2) -> 0 | N2: =SUMIFS('Por foco'!$O$2:$O$579,'Por foco'!$A$2:$A$579,$A2,'Por foco'!$B$2:$B$579,$B2) -> 0 | O2: =SUMIFS('Por foco'!$P$2:$P$579,'Por foco'!$A$2:$A$579,$A2,'Por foco'!$B$2:$B$579,$B2) -> 0 | P2: =SUMIFS('Por foco'!$Q$2:$Q$579,'Por foco'!$A$2:$A$579,$A2,'Por foco'!$B$2:$B$579,$B2) -> 0 | Q2: =SUMIFS('Por foco'!$R$2:$R$579,'Por foco'!$A$2:$A$579,$A2,'Por foco'!$B$2:$B$579,$B2) -> 0 | R2: =SUMIFS('Por foco'!$S$2:$S$579,'Por foco'!$A$2:$A$579,$A2,'Por foco'!$B$2:$B$579,$B2) -> 0 | S2: =SUMIFS('Por foco'!$T$2:$T$579,'Por foco'!$A$2:$A$579,$A2,'Por foco'!$B$2:$B$579,$B2) -> 0 | T2: =SUMIFS('Por foco'!$U$2:$U$579,'Por foco'!$A$2:$A$579,$A2,'Por foco'!$B$2:$B$579,$B2) -> 0 | U2: =SUMIFS('Por foco'!$V$2:$V$579,'Por foco'!$A$2:$A$579,$A2,'Por foco'!$B$2:$B$579,$B2) -> 0 | V2: =SUMIFS('Por foco'!$W$2:$W$579,'Por foco'!$A$2:$A$579,$A2,'Por foco'!$B$2:$B$579,$B2) -> 2 | W2: =SUMIFS('Por foco'!$X$2:$X$579,'Por foco'!$A$2:$A$579,$A2,'Por foco'!$B$2:$B$579,$B2) -> 4
A3: EFE | B3: el_monte | C3: =COUNTIFS('Por foco'!$A$2:$A$579,$A3,'Por foco'!$B$2:$B$579,$B3) -> 9 | D3: =SUMIFS('Por foco'!$E$2:$E$579,'Por foco'!$A$2:$A$579,$A3,'Por foco'!$B$2:$B$579,$B3) -> 539 | E3: =SUMIFS('Por foco'!$F$2:$F$579,'Por foco'!$A$2:$A$579,$A3,'Por foco'!$B$2:$B$579,$B3) -> 0 | F3: =SUMIFS('Por foco'!$G$2:$G$579,'Por foco'!$A$2:$A$579,$A3,'Por foco'!$B$2:$B$579,$B3) -> 0 | G3: =SUMIFS('Por foco'!$H$2:$H$579,'Por foco'!$A$2:$A$579,$A3,'Por foco'!$B$2:$B$579,$B3) -> 0 | H3: =SUMIFS('Por foco'!$I$2:$I$579,'Por foco'!$A$2:$A$579,$A3,'Por foco'!$B$2:$B$579,$B3) -> 30000 | I3: =SUMIFS('Por foco'!$J$2:$J$579,'Por foco'!$A$2:$A$579,$A3,'Por foco'!$B$2:$B$579,$B3) -> 0 | J3: =SUMIFS('Por foco'!$K$2:$K$579,'Por foco'!$A$2:$A$579,$A3,'Por foco'!$B$2:$B$579,$B3) -> 0 | K3: =SUMIFS('Por foco'!$L$2:$L$579,'Por foco'!$A$2:$A$579,$A3,'Por foco'!$B$2:$B$579,$B3) -> 0 | L3: =SUMIFS('Por foco'!$M$2:$M$579,'Por foco'!$A$2:$A$579,$A3,'Por foco'!$B$2:$B$579,$B3) -> 0 | M3: =SUMIFS('Por foco'!$N$2:$N$579,'Por foco'!$A$2:$A$579,$A3,'Por foco'!$B$2:$B$579,$B3) -> 2 | N3: =SUMIFS('Por foco'!$O$2:$O$579,'Por foco'!$A$2:$A$579,$A3,'Por foco'!$B$2:$B$579,$B3) -> 0 | O3: =SUMIFS('Por foco'!$P$2:$P$579,'Por foco'!$A$2:$A$579,$A3,'Por foco'!$B$2:$B$579,$B3) -> 3 | P3: =SUMIFS('Por foco'!$Q$2:$Q$579,'Por foco'!$A$2:$A$579,$A3,'Por foco'!$B$2:$B$579,$B3) -> 0 | Q3: =SUMIFS('Por foco'!$R$2:$R$579,'Por foco'!$A$2:$A$579,$A3,'Por foco'!$B$2:$B$579,$B3) -> 0 | R3: =SUMIFS('Por foco'!$S$2:$S$579,'Por foco'!$A$2:$A$579,$A3,'Por foco'!$B$2:$B$579,$B3) -> 0 | S3: =SUMIFS('Por foco'!$T$2:$T$579,'Por foco'!$A$2:$A$579,$A3,'Por foco'!$B$2:$B$579,$B3) -> 0 | T3: =SUMIFS('Por foco'!$U$2:$U$579,'Por foco'!$A$2:$A$579,$A3,'Por foco'!$B$2:$B$579,$B3) -> 0 | U3: =SUMIFS('Por foco'!$V$2:$V$579,'Por foco'!$A$2:$A$579,$A3,'Por foco'!$B$2:$B$579,$B3) -> 0 | V3: =SUMIFS('Por foco'!$W$2:$W$579,'Por foco'!$A$2:$A$579,$A3,'Por foco'!$B$2:$B$579,$B3) -> 1 | W3: =SUMIFS('Por foco'!$X$2:$X$579,'Por foco'!$A$2:$A$579,$A3,'Por foco'!$B$2:$B$579,$B3) -> 8
A4: EFE | B4: destino | C4: =COUNTIFS('Por foco'!$A$2:$A$579,$A4,'Por foco'!$B$2:$B$579,$B4) -> 4 | D4: =SUMIFS('Por foco'!$E$2:$E$579,'Por foco'!$A$2:$A$579,$A4,'Por foco'!$B$2:$B$579,$B4) -> 315 | E4: =SUMIFS('Por foco'!$F$2:$F$579,'Por foco'!$A$2:$A$579,$A4,'Por foco'!$B$2:$B$579,$B4) -> 170 | F4: =SUMIFS('Por foco'!$G$2:$G$579,'Por foco'!$A$2:$A$579,$A4,'Por foco'!$B$2:$B$579,$B4) -> 5 | G4: =SUMIFS('Por foco'!$H$2:$H$579,'Por foco'!$A$2:$A$579,$A4,'Por foco'!$B$2:$B$579,$B4) -> 5 | H4: =SUMIFS('Por foco'!$I$2:$I$579,'Por foco'!$A$2:$A$579,$A4,'Por foco'!$B$2:$B$579,$B4) -> 0 | I4: =SUMIFS('Por foco'!$J$2:$J$579,'Por foco'!$A$2:$A$579,$A4,'Por foco'!$B$2:$B$579,$B4) -> 25 | J4: =SUMIFS('Por foco'!$K$2:$K$579,'Por foco'!$A$2:$A$579,$A4,'Por foco'!$B$2:$B$579,$B4) -> 0 | K4: =SUMIFS('Por foco'!$L$2:$L$579,'Por foco'!$A$2:$A$579,$A4,'Por foco'!$B$2:$B$579,$B4) -> 0 | L4: =SUMIFS('Por foco'!$M$2:$M$579,'Por foco'!$A$2:$A$579,$A4,'Por foco'!$B$2:$B$579,$B4) -> 0 | M4: =SUMIFS('Por foco'!$N$2:$N$579,'Por foco'!$A$2:$A$579,$A4,'Por foco'!$B$2:$B$579,$B4) -> 0 | N4: =SUMIFS('Por foco'!$O$2:$O$579,'Por foco'!$A$2:$A$579,$A4,'Por foco'!$B$2:$B$579,$B4) -> 0 | O4: =SUMIFS('Por foco'!$P$2:$P$579,'Por foco'!$A$2:$A$579,$A4,'Por foco'!$B$2:$B$579,$B4) -> 0 | P4: =SUMIFS('Por foco'!$Q$2:$Q$579,'Por foco'!$A$2:$A$579,$A4,'Por foco'!$B$2:$B$579,$B4) -> 0 | Q4: =SUMIFS('Por foco'!$R$2:$R$579,'Por foco'!$A$2:$A$579,$A4,'Por foco'!$B$2:$B$579,$B4) -> 0 | R4: =SUMIFS('Por foco'!$S$2:$S$579,'Por foco'!$A$2:$A$579,$A4,'Por foco'!$B$2:$B$579,$B4) -> 0 | S4: =SUMIFS('Por foco'!$T$2:$T$579,'Por foco'!$A$2:$A$579,$A4,'Por foco'!$B$2:$B$579,$B4) -> 0 | T4: =SUMIFS('Por foco'!$U$2:$U$579,'Por foco'!$A$2:$A$579,$A4,'Por foco'!$B$2:$B$579,$B4) -> 0 | U4: =SUMIFS('Por foco'!$V$2:$V$579,'Por foco'!$A$2:$A$579,$A4,'Por foco'!$B$2:$B$579,$B4) -> 0 | V4: =SUMIFS('Por foco'!$W$2:$W$579,'Por foco'!$A$2:$A$579,$A4,'Por foco'!$B$2:$B$579,$B4) -> 8 | W4: =SUMIFS('Por foco'!$X$2:$X$579,'Por foco'!$A$2:$A$579,$A4,'Por foco'!$B$2:$B$579,$B4) -> 1
A5: EFE | B5: autarquia | C5: =COUNTIFS('Por foco'!$A$2:$A$579,$A5,'Por foco'!$B$2:$B$579,$B5) -> 8 | D5: =SUMIFS('Por foco'!$E$2:$E$579,'Por foco'!$A$2:$A$579,$A5,'Por foco'!$B$2:$B$579,$B5) -> 532 | E5: =SUMIFS('Por foco'!$F$2:$F$579,'Por foco'!$A$2:$A$579,$A5,'Por foco'!$B$2:$B$579,$B5) -> 250 | F5: =SUMIFS('Por foco'!$G$2:$G$579,'Por foco'!$A$2:$A$579,$A5,'Por foco'!$B$2:$B$579,$B5) -> -5 | G5: =SUMIFS('Por foco'!$H$2:$H$579,'Por foco'!$A$2:$A$579,$A5,'Por foco'!$B$2:$B$579,$B5) -> 0 | H5: =SUMIFS('Por foco'!$I$2:$I$579,'Por foco'!$A$2:$A$579,$A5,'Por foco'!$B$2:$B$579,$B5) -> 0 | I5: =SUMIFS('Por foco'!$J$2:$J$579,'Por foco'!$A$2:$A$579,$A5,'Por foco'!$B$2:$B$579,$B5) -> 0 | J5: =SUMIFS('Por foco'!$K$2:$K$579,'Por foco'!$A$2:$A$579,$A5,'Por foco'!$B$2:$B$579,$B5) -> 0 | K5: =SUMIFS('Por foco'!$L$2:$L$579,'Por foco'!$A$2:$A$579,$A5,'Por foco'!$B$2:$B$579,$B5) -> 0 | L5: =SUMIFS('Por foco'!$M$2:$M$579,'Por foco'!$A$2:$A$579,$A5,'Por foco'!$B$2:$B$579,$B5) -> 0 | M5: =SUMIFS('Por foco'!$N$2:$N$579,'Por foco'!$A$2:$A$579,$A5,'Por foco'!$B$2:$B$579,$B5) -> 2 | N5: =SUMIFS('Por foco'!$O$2:$O$579,'Por foco'!$A$2:$A$579,$A5,'Por foco'!$B$2:$B$579,$B5) -> 5 | O5: =SUMIFS('Por foco'!$P$2:$P$579,'Por foco'!$A$2:$A$579,$A5,'Por foco'!$B$2:$B$579,$B5) -> 2 | P5: =SUMIFS('Por foco'!$Q$2:$Q$579,'Por foco'!$A$2:$A$579,$A5,'Por foco'!$B$2:$B$579,$B5) -> 0 | Q5: =SUMIFS('Por foco'!$R$2:$R$579,'Por foco'!$A$2:$A$579,$A5,'Por foco'!$B$2:$B$579,$B5) -> 0 | R5: =SUMIFS('Por foco'!$S$2:$S$579,'Por foco'!$A$2:$A$579,$A5,'Por foco'!$B$2:$B$579,$B5) -> 0 | S5: =SUMIFS('Por foco'!$T$2:$T$579,'Por foco'!$A$2:$A$579,$A5,'Por foco'!$B$2:$B$579,$B5) -> 0 | T5: =SUMIFS('Por foco'!$U$2:$U$579,'Por foco'!$A$2:$A$579,$A5,'Por foco'!$B$2:$B$579,$B5) -> 0 | U5: =SUMIFS('Por foco'!$V$2:$V$579,'Por foco'!$A$2:$A$579,$A5,'Por foco'!$B$2:$B$579,$B5) -> 0 | V5: =SUMIFS('Por foco'!$W$2:$W$579,'Por foco'!$A$2:$A$579,$A5,'Por foco'!$B$2:$B$579,$B5) -> 0 | W5: =SUMIFS('Por foco'!$X$2:$X$579,'Por foco'!$A$2:$A$579,$A5,'Por foco'!$B$2:$B$579,$B5) -> 3
A6: EFE | B6: diplomacia_agua | C6: =COUNTIFS('Por foco'!$A$2:$A$579,$A6,'Por foco'!$B$2:$B$579,$B6) -> 7 | D6: =SUMIFS('Por foco'!$E$2:$E$579,'Por foco'!$A$2:$A$579,$A6,'Por foco'!$B$2:$B$579,$B6) -> 483 | E6: =SUMIFS('Por foco'!$F$2:$F$579,'Por foco'!$A$2:$A$579,$A6,'Por foco'!$B$2:$B$579,$B6) -> 200 | F6: =SUMIFS('Por foco'!$G$2:$G$579,'Por foco'!$A$2:$A$579,$A6,'Por foco'!$B$2:$B$579,$B6) -> 0 | G6: =SUMIFS('Por foco'!$H$2:$H$579,'Por foco'!$A$2:$A$579,$A6,'Por foco'!$B$2:$B$579,$B6) -> 0 | H6: =SUMIFS('Por foco'!$I$2:$I$579,'Por foco'!$A$2:$A$579,$A6,'Por foco'!$B$2:$B$579,$B6) -> 0 | I6: =SUMIFS('Por foco'!$J$2:$J$579,'Por foco'!$A$2:$A$579,$A6,'Por foco'!$B$2:$B$579,$B6) -> 0 | J6: =SUMIFS('Por foco'!$K$2:$K$579,'Por foco'!$A$2:$A$579,$A6,'Por foco'!$B$2:$B$579,$B6) -> 0 | K6: =SUMIFS('Por foco'!$L$2:$L$579,'Por foco'!$A$2:$A$579,$A6,'Por foco'!$B$2:$B$579,$B6) -> 0 | L6: =SUMIFS('Por foco'!$M$2:$M$579,'Por foco'!$A$2:$A$579,$A6,'Por foco'!$B$2:$B$579,$B6) -> 0 | M6: =SUMIFS('Por foco'!$N$2:$N$579,'Por foco'!$A$2:$A$579,$A6,'Por foco'!$B$2:$B$579,$B6) -> 0 | N6: =SUMIFS('Por foco'!$O$2:$O$579,'Por foco'!$A$2:$A$579,$A6,'Por foco'!$B$2:$B$579,$B6) -> 6 | O6: =SUMIFS('Por foco'!$P$2:$P$579,'Por foco'!$A$2:$A$579,$A6,'Por foco'!$B$2:$B$579,$B6) -> 0 | P6: =SUMIFS('Por foco'!$Q$2:$Q$579,'Por foco'!$A$2:$A$579,$A6,'Por foco'!$B$2:$B$579,$B6) -> 0 | Q6: =SUMIFS('Por foco'!$R$2:$R$579,'Por foco'!$A$2:$A$579,$A6,'Por foco'!$B$2:$B$579,$B6) -> 0 | R6: =SUMIFS('Por foco'!$S$2:$S$579,'Por foco'!$A$2:$A$579,$A6,'Por foco'!$B$2:$B$579,$B6) -> 0 | S6: =SUMIFS('Por foco'!$T$2:$T$579,'Por foco'!$A$2:$A$579,$A6,'Por foco'!$B$2:$B$579,$B6) -> 0 | T6: =SUMIFS('Por foco'!$U$2:$U$579,'Por foco'!$A$2:$A$579,$A6,'Por foco'!$B$2:$B$579,$B6) -> 0 | U6: =SUMIFS('Por foco'!$V$2:$V$579,'Por foco'!$A$2:$A$579,$A6,'Por foco'!$B$2:$B$579,$B6) -> 0 | V6: =SUMIFS('Por foco'!$W$2:$W$579,'Por foco'!$A$2:$A$579,$A6,'Por foco'!$B$2:$B$579,$B6) -> 0 | W6: =SUMIFS('Por foco'!$X$2:$X$579,'Por foco'!$A$2:$A$579,$A6,'Por foco'!$B$2:$B$579,$B6) -> 3
A7: EFE | B7: cubas | C7: =COUNTIFS('Por foco'!$A$2:$A$579,$A7,'Por foco'!$B$2:$B$579,$B7) -> 6 | D7: =SUMIFS('Por foco'!$E$2:$E$579,'Por foco'!$A$2:$A$579,$A7,'Por foco'!$B$2:$B$579,$B7) -> 364 | E7: =SUMIFS('Por foco'!$F$2:$F$579,'Por foco'!$A$2:$A$579,$A7,'Por foco'!$B$2:$B$579,$B7) -> 0 | F7: =SUMIFS('Por foco'!$G$2:$G$579,'Por foco'!$A$2:$A$579,$A7,'Por foco'!$B$2:$B$579,$B7) -> 0 | G7: =SUMIFS('Por foco'!$H$2:$H$579,'Por foco'!$A$2:$A$579,$A7,'Por foco'!$B$2:$B$579,$B7) -> 0 | H7: =SUMIFS('Por foco'!$I$2:$I$579,'Por foco'!$A$2:$A$579,$A7,'Por foco'!$B$2:$B$579,$B7) -> 0 | I7: =SUMIFS('Por foco'!$J$2:$J$579,'Por foco'!$A$2:$A$579,$A7,'Por foco'!$B$2:$B$579,$B7) -> 0 | J7: =SUMIFS('Por foco'!$K$2:$K$579,'Por foco'!$A$2:$A$579,$A7,'Por foco'!$B$2:$B$579,$B7) -> 0 | K7: =SUMIFS('Por foco'!$L$2:$L$579,'Por foco'!$A$2:$A$579,$A7,'Por foco'!$B$2:$B$579,$B7) -> 0 | L7: =SUMIFS('Por foco'!$M$2:$M$579,'Por foco'!$A$2:$A$579,$A7,'Por foco'!$B$2:$B$579,$B7) -> 1 | M7: =SUMIFS('Por foco'!$N$2:$N$579,'Por foco'!$A$2:$A$579,$A7,'Por foco'!$B$2:$B$579,$B7) -> 1 | N7: =SUMIFS('Por foco'!$O$2:$O$579,'Por foco'!$A$2:$A$579,$A7,'Por foco'!$B$2:$B$579,$B7) -> 4 | O7: =SUMIFS('Por foco'!$P$2:$P$579,'Por foco'!$A$2:$A$579,$A7,'Por foco'!$B$2:$B$579,$B7) -> 2 | P7: =SUMIFS('Por foco'!$Q$2:$Q$579,'Por foco'!$A$2:$A$579,$A7,'Por foco'!$B$2:$B$579,$B7) -> 2 | Q7: =SUMIFS('Por foco'!$R$2:$R$579,'Por foco'!$A$2:$A$579,$A7,'Por foco'!$B$2:$B$579,$B7) -> 0 | R7: =SUMIFS('Por foco'!$S$2:$S$579,'Por foco'!$A$2:$A$579,$A7,'Por foco'!$B$2:$B$579,$B7) -> 0 | S7: =SUMIFS('Por foco'!$T$2:$T$579,'Por foco'!$A$2:$A$579,$A7,'Por foco'!$B$2:$B$579,$B7) -> 0 | T7: =SUMIFS('Por foco'!$U$2:$U$579,'Por foco'!$A$2:$A$579,$A7,'Por foco'!$B$2:$B$579,$B7) -> 0 | U7: =SUMIFS('Por foco'!$V$2:$V$579,'Por foco'!$A$2:$A$579,$A7,'Por foco'!$B$2:$B$579,$B7) -> 0 | V7: =SUMIFS('Por foco'!$W$2:$W$579,'Por foco'!$A$2:$A$579,$A7,'Por foco'!$B$2:$B$579,$B7) -> 0 | W7: =SUMIFS('Por foco'!$X$2:$X$579,'Por foco'!$A$2:$A$579,$A7,'Por foco'!$B$2:$B$579,$B7) -> 1
A8: EFE | B8: guardia_verde | C8: =COUNTIFS('Por foco'!$A$2:$A$579,$A8,'Por foco'!$B$2:$B$579,$B8) -> 6 | D8: =SUMIFS('Por foco'!$E$2:$E$579,'Por foco'!$A$2:$A$579,$A8,'Por foco'!$B$2:$B$579,$B8) -> 343 | E8: =SUMIFS('Por foco'!$F$2:$F$579,'Por foco'!$A$2:$A$579,$A8,'Por foco'!$B$2:$B$579,$B8) -> 0 | F8: =SUMIFS('Por foco'!$G$2:$G$579,'Por foco'!$A$2:$A$579,$A8,'Por foco'!$B$2:$B$579,$B8) -> 0 | G8: =SUMIFS('Por foco'!$H$2:$H$579,'Por foco'!$A$2:$A$579,$A8,'Por foco'!$B$2:$B$579,$B8) -> 0 | H8: =SUMIFS('Por foco'!$I$2:$I$579,'Por foco'!$A$2:$A$579,$A8,'Por foco'!$B$2:$B$579,$B8) -> 50000 | I8: =SUMIFS('Por foco'!$J$2:$J$579,'Por foco'!$A$2:$A$579,$A8,'Por foco'!$B$2:$B$579,$B8) -> 75 | J8: =SUMIFS('Por foco'!$K$2:$K$579,'Por foco'!$A$2:$A$579,$A8,'Por foco'!$B$2:$B$579,$B8) -> 0 | K8: =SUMIFS('Por foco'!$L$2:$L$579,'Por foco'!$A$2:$A$579,$A8,'Por foco'!$B$2:$B$579,$B8) -> 0 | L8: =SUMIFS('Por foco'!$M$2:$M$579,'Por foco'!$A$2:$A$579,$A8,'Por foco'!$B$2:$B$579,$B8) -> 0 | M8: =SUMIFS('Por foco'!$N$2:$N$579,'Por foco'!$A$2:$A$579,$A8,'Por foco'!$B$2:$B$579,$B8) -> 4 | N8: =SUMIFS('Por foco'!$O$2:$O$579,'Por foco'!$A$2:$A$579,$A8,'Por foco'!$B$2:$B$579,$B8) -> 0 | O8: =SUMIFS('Por foco'!$P$2:$P$579,'Por foco'!$A$2:$A$579,$A8,'Por foco'!$B$2:$B$579,$B8) -> 0 | P8: =SUMIFS('Por foco'!$Q$2:$Q$579,'Por foco'!$A$2:$A$579,$A8,'Por foco'!$B$2:$B$579,$B8) -> 0 | Q8: =SUMIFS('Por foco'!$R$2:$R$579,'Por foco'!$A$2:$A$579,$A8,'Por foco'!$B$2:$B$579,$B8) -> 0 | R8: =SUMIFS('Por foco'!$S$2:$S$579,'Por foco'!$A$2:$A$579,$A8,'Por foco'!$B$2:$B$579,$B8) -> 0 | S8: =SUMIFS('Por foco'!$T$2:$T$579,'Por foco'!$A$2:$A$579,$A8,'Por foco'!$B$2:$B$579,$B8) -> 0 | T8: =SUMIFS('Por foco'!$U$2:$U$579,'Por foco'!$A$2:$A$579,$A8,'Por foco'!$B$2:$B$579,$B8) -> 0 | U8: =SUMIFS('Por foco'!$V$2:$V$579,'Por foco'!$A$2:$A$579,$A8,'Por foco'!$B$2:$B$579,$B8) -> 0 | V8: =SUMIFS('Por foco'!$W$2:$W$579,'Por foco'!$A$2:$A$579,$A8,'Por foco'!$B$2:$B$579,$B8) -> 0 | W8: =SUMIFS('Por foco'!$X$2:$X$579,'Por foco'!$A$2:$A$579,$A8,'Por foco'!$B$2:$B$579,$B8) -> 3
A9: EFE | B9: condores | C9: =COUNTIFS('Por foco'!$A$2:$A$579,$A9,'Por foco'!$B$2:$B$579,$B9) -> 6 | D9: =SUMIFS('Por foco'!$E$2:$E$579,'Por foco'!$A$2:$A$579,$A9,'Por foco'!$B$2:$B$579,$B9) -> 343 | E9: =SUMIFS('Por foco'!$F$2:$F$579,'Por foco'!$A$2:$A$579,$A9,'Por foco'!$B$2:$B$579,$B9) -> 0 | F9: =SUMIFS('Por foco'!$G$2:$G$579,'Por foco'!$A$2:$A$579,$A9,'Por foco'!$B$2:$B$579,$B9) -> 0 | G9: =SUMIFS('Por foco'!$H$2:$H$579,'Por foco'!$A$2:$A$579,$A9,'Por foco'!$B$2:$B$579,$B9) -> 5 | H9: =SUMIFS('Por foco'!$I$2:$I$579,'Por foco'!$A$2:$A$579,$A9,'Por foco'!$B$2:$B$579,$B9) -> 0 | I9: =SUMIFS('Por foco'!$J$2:$J$579,'Por foco'!$A$2:$A$579,$A9,'Por foco'!$B$2:$B$579,$B9) -> 0 | J9: =SUMIFS('Por foco'!$K$2:$K$579,'Por foco'!$A$2:$A$579,$A9,'Por foco'!$B$2:$B$579,$B9) -> 0 | K9: =SUMIFS('Por foco'!$L$2:$L$579,'Por foco'!$A$2:$A$579,$A9,'Por foco'!$B$2:$B$579,$B9) -> 75 | L9: =SUMIFS('Por foco'!$M$2:$M$579,'Por foco'!$A$2:$A$579,$A9,'Por foco'!$B$2:$B$579,$B9) -> 0 | M9: =SUMIFS('Por foco'!$N$2:$N$579,'Por foco'!$A$2:$A$579,$A9,'Por foco'!$B$2:$B$579,$B9) -> 5 | N9: =SUMIFS('Por foco'!$O$2:$O$579,'Por foco'!$A$2:$A$579,$A9,'Por foco'!$B$2:$B$579,$B9) -> 0 | O9: =SUMIFS('Por foco'!$P$2:$P$579,'Por foco'!$A$2:$A$579,$A9,'Por foco'!$B$2:$B$579,$B9) -> 0 | P9: =SUMIFS('Por foco'!$Q$2:$Q$579,'Por foco'!$A$2:$A$579,$A9,'Por foco'!$B$2:$B$579,$B9) -> 2 | Q9: =SUMIFS('Por foco'!$R$2:$R$579,'Por foco'!$A$2:$A$579,$A9,'Por foco'!$B$2:$B$579,$B9) -> 0 | R9: =SUMIFS('Por foco'!$S$2:$S$579,'Por foco'!$A$2:$A$579,$A9,'Por foco'!$B$2:$B$579,$B9) -> 2 | S9: =SUMIFS('Por foco'!$T$2:$T$579,'Por foco'!$A$2:$A$579,$A9,'Por foco'!$B$2:$B$579,$B9) -> 0 | T9: =SUMIFS('Por foco'!$U$2:$U$579,'Por foco'!$A$2:$A$579,$A9,'Por foco'!$B$2:$B$579,$B9) -> 0 | U9: =SUMIFS('Por foco'!$V$2:$V$579,'Por foco'!$A$2:$A$579,$A9,'Por foco'!$B$2:$B$579,$B9) -> 150 | V9: =SUMIFS('Por foco'!$W$2:$W$579,'Por foco'!$A$2:$A$579,$A9,'Por foco'!$B$2:$B$579,$B9) -> 0 | W9: =SUMIFS('Por foco'!$X$2:$X$579,'Por foco'!$A$2:$A$579,$A9,'Por foco'!$B$2:$B$579,$B9) -> 0
A10: EFE | B10: ciclo_bioacero | C10: =COUNTIFS('Por foco'!$A$2:$A$579,$A10,'Por foco'!$B$2:$B$579,$B10) -> 7 | D10: =SUMIFS('Por foco'!$E$2:$E$579,'Por foco'!$A$2:$A$579,$A10,'Por foco'!$B$2:$B$579,$B10) -> 448 | E10: =SUMIFS('Por foco'!$F$2:$F$579,'Por foco'!$A$2:$A$579,$A10,'Por foco'!$B$2:$B$579,$B10) -> 150 | F10: =SUMIFS('Por foco'!$G$2:$G$579,'Por foco'!$A$2:$A$579,$A10,'Por foco'!$B$2:$B$579,$B10) -> 0 | G10: =SUMIFS('Por foco'!$H$2:$H$579,'Por foco'!$A$2:$A$579,$A10,'Por foco'!$B$2:$B$579,$B10) -> 0 | H10: =SUMIFS('Por foco'!$I$2:$I$579,'Por foco'!$A$2:$A$579,$A10,'Por foco'!$B$2:$B$579,$B10) -> 0 | I10: =SUMIFS('Por foco'!$J$2:$J$579,'Por foco'!$A$2:$A$579,$A10,'Por foco'!$B$2:$B$579,$B10) -> 0 | J10: =SUMIFS('Por foco'!$K$2:$K$579,'Por foco'!$A$2:$A$579,$A10,'Por foco'!$B$2:$B$579,$B10) -> 0 | K10: =SUMIFS('Por foco'!$L$2:$L$579,'Por foco'!$A$2:$A$579,$A10,'Por foco'!$B$2:$B$579,$B10) -> 0 | L10: =SUMIFS('Por foco'!$M$2:$M$579,'Por foco'!$A$2:$A$579,$A10,'Por foco'!$B$2:$B$579,$B10) -> 1 | M10: =SUMIFS('Por foco'!$N$2:$N$579,'Por foco'!$A$2:$A$579,$A10,'Por foco'!$B$2:$B$579,$B10) -> 0 | N10: =SUMIFS('Por foco'!$O$2:$O$579,'Por foco'!$A$2:$A$579,$A10,'Por foco'!$B$2:$B$579,$B10) -> 0 | O10: =SUMIFS('Por foco'!$P$2:$P$579,'Por foco'!$A$2:$A$579,$A10,'Por foco'!$B$2:$B$579,$B10) -> 0 | P10: =SUMIFS('Por foco'!$Q$2:$Q$579,'Por foco'!$A$2:$A$579,$A10,'Por foco'!$B$2:$B$579,$B10) -> 0 | Q10: =SUMIFS('Por foco'!$R$2:$R$579,'Por foco'!$A$2:$A$579,$A10,'Por foco'!$B$2:$B$579,$B10) -> 0 | R10: =SUMIFS('Por foco'!$S$2:$S$579,'Por foco'!$A$2:$A$579,$A10,'Por foco'!$B$2:$B$579,$B10) -> 0 | S10: =SUMIFS('Por foco'!$T$2:$T$579,'Por foco'!$A$2:$A$579,$A10,'Por foco'!$B$2:$B$579,$B10) -> 0 | T10: =SUMIFS('Por foco'!$U$2:$U$579,'Por foco'!$A$2:$A$579,$A10,'Por foco'!$B$2:$B$579,$B10) -> 0 | U10: =SUMIFS('Por foco'!$V$2:$V$579,'Por foco'!$A$2:$A$579,$A10,'Por foco'!$B$2:$B$579,$B10) -> 0 | V10: =SUMIFS('Por foco'!$W$2:$W$579,'Por foco'!$A$2:$A$579,$A10,'Por foco'!$B$2:$B$579,$B10) -> 0 | W10: =SUMIFS('Por foco'!$X$2:$X$579,'Por foco'!$A$2:$A$579,$A10,'Por foco'!$B$2:$B$579,$B10) -> 3
A11: EFE | B11: cubas_sanas | C11: =COUNTIFS('Por foco'!$A$2:$A$579,$A11,'Por foco'!$B$2:$B$579,$B11) -> 6 | D11: =SUMIFS('Por foco'!$E$2:$E$579,'Por foco'!$A$2:$A$579,$A11,'Por foco'!$B$2:$B$579,$B11) -> 413 | E11: =SUMIFS('Por foco'!$F$2:$F$579,'Por foco'!$A$2:$A$579,$A11,'Por foco'!$B$2:$B$579,$B11) -> 100 | F11: =SUMIFS('Por foco'!$G$2:$G$579,'Por foco'!$A$2:$A$579,$A11,'Por foco'!$B$2:$B$579,$B11) -> 0 | G11: =SUMIFS('Por foco'!$H$2:$H$579,'Por foco'!$A$2:$A$579,$A11,'Por foco'!$B$2:$B$579,$B11) -> 0 | H11: =SUMIFS('Por foco'!$I$2:$I$579,'Por foco'!$A$2:$A$579,$A11,'Por foco'!$B$2:$B$579,$B11) -> 0 | I11: =SUMIFS('Por foco'!$J$2:$J$579,'Por foco'!$A$2:$A$579,$A11,'Por foco'!$B$2:$B$579,$B11) -> 0 | J11: =SUMIFS('Por foco'!$K$2:$K$579,'Por foco'!$A$2:$A$579,$A11,'Por foco'!$B$2:$B$579,$B11) -> 0 | K11: =SUMIFS('Por foco'!$L$2:$L$579,'Por foco'!$A$2:$A$579,$A11,'Por foco'!$B$2:$B$579,$B11) -> 0 | L11: =SUMIFS('Por foco'!$M$2:$M$579,'Por foco'!$A$2:$A$579,$A11,'Por foco'!$B$2:$B$579,$B11) -> 0 | M11: =SUMIFS('Por foco'!$N$2:$N$579,'Por foco'!$A$2:$A$579,$A11,'Por foco'!$B$2:$B$579,$B11) -> 2 | N11: =SUMIFS('Por foco'!$O$2:$O$579,'Por foco'!$A$2:$A$579,$A11,'Por foco'!$B$2:$B$579,$B11) -> 2 | O11: =SUMIFS('Por foco'!$P$2:$P$579,'Por foco'!$A$2:$A$579,$A11,'Por foco'!$B$2:$B$579,$B11) -> 0 | P11: =SUMIFS('Por foco'!$Q$2:$Q$579,'Por foco'!$A$2:$A$579,$A11,'Por foco'!$B$2:$B$579,$B11) -> 0 | Q11: =SUMIFS('Por foco'!$R$2:$R$579,'Por foco'!$A$2:$A$579,$A11,'Por foco'!$B$2:$B$579,$B11) -> 0 | R11: =SUMIFS('Por foco'!$S$2:$S$579,'Por foco'!$A$2:$A$579,$A11,'Por foco'!$B$2:$B$579,$B11) -> 0 | S11: =SUMIFS('Por foco'!$T$2:$T$579,'Por foco'!$A$2:$A$579,$A11,'Por foco'!$B$2:$B$579,$B11) -> 0 | T11: =SUMIFS('Por foco'!$U$2:$U$579,'Por foco'!$A$2:$A$579,$A11,'Por foco'!$B$2:$B$579,$B11) -> 0 | U11: =SUMIFS('Por foco'!$V$2:$V$579,'Por foco'!$A$2:$A$579,$A11,'Por foco'!$B$2:$B$579,$B11) -> 0 | V11: =SUMIFS('Por foco'!$W$2:$W$579,'Por foco'!$A$2:$A$579,$A11,'Por foco'!$B$2:$B$579,$B11) -> 0 | W11: =SUMIFS('Por foco'!$X$2:$X$579,'Por foco'!$A$2:$A$579,$A11,'Por foco'!$B$2:$B$579,$B11) -> 3
A12: ASC | B12: consejo_sorteado | C12: =COUNTIFS('Por foco'!$A$2:$A$579,$A12,'Por foco'!$B$2:$B$579,$B12) -> 9 | D12: =SUMIFS('Por foco'!$E$2:$E$579,'Por foco'!$A$2:$A$579,$A12,'Por foco'!$B$2:$B$579,$B12) -> 560 | E12: =SUMIFS('Por foco'!$F$2:$F$579,'Por foco'!$A$2:$A$579,$A12,'Por foco'!$B$2:$B$579,$B12) -> 300 | F12: =SUMIFS('Por foco'!$G$2:$G$579,'Por foco'!$A$2:$A$579,$A12,'Por foco'!$B$2:$B$579,$B12) -> 0 | G12: =SUMIFS('Por foco'!$H$2:$H$579,'Por foco'!$A$2:$A$579,$A12,'Por foco'!$B$2:$B$579,$B12) -> 5 | H12: =SUMIFS('Por foco'!$I$2:$I$579,'Por foco'!$A$2:$A$579,$A12,'Por foco'!$B$2:$B$579,$B12) -> 0 | I12: =SUMIFS('Por foco'!$J$2:$J$579,'Por foco'!$A$2:$A$579,$A12,'Por foco'!$B$2:$B$579,$B12) -> 50 | J12: =SUMIFS('Por foco'!$K$2:$K$579,'Por foco'!$A$2:$A$579,$A12,'Por foco'!$B$2:$B$579,$B12) -> 0 | K12: =SUMIFS('Por foco'!$L$2:$L$579,'Por foco'!$A$2:$A$579,$A12,'Por foco'!$B$2:$B$579,$B12) -> 0 | L12: =SUMIFS('Por foco'!$M$2:$M$579,'Por foco'!$A$2:$A$579,$A12,'Por foco'!$B$2:$B$579,$B12) -> 1 | M12: =SUMIFS('Por foco'!$N$2:$N$579,'Por foco'!$A$2:$A$579,$A12,'Por foco'!$B$2:$B$579,$B12) -> 0 | N12: =SUMIFS('Por foco'!$O$2:$O$579,'Por foco'!$A$2:$A$579,$A12,'Por foco'!$B$2:$B$579,$B12) -> 0 | O12: =SUMIFS('Por foco'!$P$2:$P$579,'Por foco'!$A$2:$A$579,$A12,'Por foco'!$B$2:$B$579,$B12) -> 0 | P12: =SUMIFS('Por foco'!$Q$2:$Q$579,'Por foco'!$A$2:$A$579,$A12,'Por foco'!$B$2:$B$579,$B12) -> 0 | Q12: =SUMIFS('Por foco'!$R$2:$R$579,'Por foco'!$A$2:$A$579,$A12,'Por foco'!$B$2:$B$579,$B12) -> 0 | R12: =SUMIFS('Por foco'!$S$2:$S$579,'Por foco'!$A$2:$A$579,$A12,'Por foco'!$B$2:$B$579,$B12) -> 0 | S12: =SUMIFS('Por foco'!$T$2:$T$579,'Por foco'!$A$2:$A$579,$A12,'Por foco'!$B$2:$B$579,$B12) -> 0 | T12: =SUMIFS('Por foco'!$U$2:$U$579,'Por foco'!$A$2:$A$579,$A12,'Por foco'!$B$2:$B$579,$B12) -> 0 | U12: =SUMIFS('Por foco'!$V$2:$V$579,'Por foco'!$A$2:$A$579,$A12,'Por foco'!$B$2:$B$579,$B12) -> 0 | V12: =SUMIFS('Por foco'!$W$2:$W$579,'Por foco'!$A$2:$A$579,$A12,'Por foco'!$B$2:$B$579,$B12) -> 1 | W12: =SUMIFS('Por foco'!$X$2:$X$579,'Por foco'!$A$2:$A$579,$A12,'Por foco'!$B$2:$B$579,$B12) -> 5
A13: ASC | B13: plan_41 | C13: =COUNTIFS('Por foco'!$A$2:$A$579,$A13,'Por foco'!$B$2:$B$579,$B13) -> 9 | D13: =SUMIFS('Por foco'!$E$2:$E$579,'Por foco'!$A$2:$A$579,$A13,'Por foco'!$B$2:$B$579,$B13) -> 595 | E13: =SUMIFS('Por foco'!$F$2:$F$579,'Por foco'!$A$2:$A$579,$A13,'Por foco'!$B$2:$B$579,$B13) -> 100 | F13: =SUMIFS('Por foco'!$G$2:$G$579,'Por foco'!$A$2:$A$579,$A13,'Por foco'!$B$2:$B$579,$B13) -> 0 | G13: =SUMIFS('Por foco'!$H$2:$H$579,'Por foco'!$A$2:$A$579,$A13,'Por foco'!$B$2:$B$579,$B13) -> 5 | H13: =SUMIFS('Por foco'!$I$2:$I$579,'Por foco'!$A$2:$A$579,$A13,'Por foco'!$B$2:$B$579,$B13) -> 100000 | I13: =SUMIFS('Por foco'!$J$2:$J$579,'Por foco'!$A$2:$A$579,$A13,'Por foco'!$B$2:$B$579,$B13) -> 0 | J13: =SUMIFS('Por foco'!$K$2:$K$579,'Por foco'!$A$2:$A$579,$A13,'Por foco'!$B$2:$B$579,$B13) -> 0 | K13: =SUMIFS('Por foco'!$L$2:$L$579,'Por foco'!$A$2:$A$579,$A13,'Por foco'!$B$2:$B$579,$B13) -> 0 | L13: =SUMIFS('Por foco'!$M$2:$M$579,'Por foco'!$A$2:$A$579,$A13,'Por foco'!$B$2:$B$579,$B13) -> 1 | M13: =SUMIFS('Por foco'!$N$2:$N$579,'Por foco'!$A$2:$A$579,$A13,'Por foco'!$B$2:$B$579,$B13) -> 2 | N13: =SUMIFS('Por foco'!$O$2:$O$579,'Por foco'!$A$2:$A$579,$A13,'Por foco'!$B$2:$B$579,$B13) -> 0 | O13: =SUMIFS('Por foco'!$P$2:$P$579,'Por foco'!$A$2:$A$579,$A13,'Por foco'!$B$2:$B$579,$B13) -> 0 | P13: =SUMIFS('Por foco'!$Q$2:$Q$579,'Por foco'!$A$2:$A$579,$A13,'Por foco'!$B$2:$B$579,$B13) -> 0 | Q13: =SUMIFS('Por foco'!$R$2:$R$579,'Por foco'!$A$2:$A$579,$A13,'Por foco'!$B$2:$B$579,$B13) -> 0 | R13: =SUMIFS('Por foco'!$S$2:$S$579,'Por foco'!$A$2:$A$579,$A13,'Por foco'!$B$2:$B$579,$B13) -> 0 | S13: =SUMIFS('Por foco'!$T$2:$T$579,'Por foco'!$A$2:$A$579,$A13,'Por foco'!$B$2:$B$579,$B13) -> 0 | T13: =SUMIFS('Por foco'!$U$2:$U$579,'Por foco'!$A$2:$A$579,$A13,'Por foco'!$B$2:$B$579,$B13) -> 0 | U13: =SUMIFS('Por foco'!$V$2:$V$579,'Por foco'!$A$2:$A$579,$A13,'Por foco'!$B$2:$B$579,$B13) -> 0 | V13: =SUMIFS('Por foco'!$W$2:$W$579,'Por foco'!$A$2:$A$579,$A13,'Por foco'!$B$2:$B$579,$B13) -> 0 | W13: =SUMIFS('Por foco'!$X$2:$X$579,'Por foco'!$A$2:$A$579,$A13,'Por foco'!$B$2:$B$579,$B13) -> 3
... A87: JUNTA | B87: mando_supremo | C87: =COUNTIFS('Por foco'!$A$2:$A$579,$A87,'Por foco'!$B$2:$B$579,$B87) -> 1 | D87: =SUMIFS('Por foco'!$E$2:$E$579,'Por foco'!$A$2:$A$579,$A87,'Por foco'!$B$2:$B$579,$B87) -> 70 | E87: =SUMIFS('Por foco'!$F$2:$F$579,'Por foco'!$A$2:$A$579,$A87,'Por foco'!$B$2:$B$579,$B87) -> 0 | F87: =SUMIFS('Por foco'!$G$2:$G$579,'Por foco'!$A$2:$A$579,$A87,'Por foco'!$B$2:$B$579,$B87) -> 0 | G87: =SUMIFS('Por foco'!$H$2:$H$579,'Por foco'!$A$2:$A$579,$A87,'Por foco'!$B$2:$B$579,$B87) -> 0 | H87: =SUMIFS('Por foco'!$I$2:$I$579,'Por foco'!$A$2:$A$579,$A87,'Por foco'!$B$2:$B$579,$B87) -> 500000 | I87: =SUMIFS('Por foco'!$J$2:$J$579,'Por foco'!$A$2:$A$579,$A87,'Por foco'!$B$2:$B$579,$B87) -> 0 | J87: =SUMIFS('Por foco'!$K$2:$K$579,'Por foco'!$A$2:$A$579,$A87,'Por foco'!$B$2:$B$579,$B87) -> 0 | K87: =SUMIFS('Por foco'!$L$2:$L$579,'Por foco'!$A$2:$A$579,$A87,'Por foco'!$B$2:$B$579,$B87) -> 0 | L87: =SUMIFS('Por foco'!$M$2:$M$579,'Por foco'!$A$2:$A$579,$A87,'Por foco'!$B$2:$B$579,$B87) -> 0 | M87: =SUMIFS('Por foco'!$N$2:$N$579,'Por foco'!$A$2:$A$579,$A87,'Por foco'!$B$2:$B$579,$B87) -> 0 | N87: =SUMIFS('Por foco'!$O$2:$O$579,'Por foco'!$A$2:$A$579,$A87,'Por foco'!$B$2:$B$579,$B87) -> 0 | O87: =SUMIFS('Por foco'!$P$2:$P$579,'Por foco'!$A$2:$A$579,$A87,'Por foco'!$B$2:$B$579,$B87) -> 0 | P87: =SUMIFS('Por foco'!$Q$2:$Q$579,'Por foco'!$A$2:$A$579,$A87,'Por foco'!$B$2:$B$579,$B87) -> 0 | Q87: =SUMIFS('Por foco'!$R$2:$R$579,'Por foco'!$A$2:$A$579,$A87,'Por foco'!$B$2:$B$579,$B87) -> 0 | R87: =SUMIFS('Por foco'!$S$2:$S$579,'Por foco'!$A$2:$A$579,$A87,'Por foco'!$B$2:$B$579,$B87) -> 0 | S87: =SUMIFS('Por foco'!$T$2:$T$579,'Por foco'!$A$2:$A$579,$A87,'Por foco'!$B$2:$B$579,$B87) -> 80000 | T87: =SUMIFS('Por foco'!$U$2:$U$579,'Por foco'!$A$2:$A$579,$A87,'Por foco'!$B$2:$B$579,$B87) -> 0 | U87: =SUMIFS('Por foco'!$V$2:$V$579,'Por foco'!$A$2:$A$579,$A87,'Por foco'!$B$2:$B$579,$B87) -> 0 | V87: =SUMIFS('Por foco'!$W$2:$W$579,'Por foco'!$A$2:$A$579,$A87,'Por foco'!$B$2:$B$579,$B87) -> 0 | W87: =SUMIFS('Por foco'!$X$2:$X$579,'Por foco'!$A$2:$A$579,$A87,'Por foco'!$B$2:$B$579,$B87) -> 1

Sheet Por foco
A1: Árbol | B1: Rama | C1: Foco | D1: Nombre | E1: Días | F1: Poder político | G1: Estabilidad (%) | H1: Apoyo a la guerra (%) | I1: Mano de obra | J1: Exp. ejército | K1: Exp. naval | L1: Exp. aérea | M1: Casillas de investigación | N1: Bonos de tecnología (usos) | O1: Fábricas civiles | P1: Fábricas militares | Q1: Astilleros | R1: Infraestructura | S1: Otros edificios (niveles) | T1: Equipo (unidades) | U1: Divisiones | V1: Cazas gratis | W1: Reclamos, núcleos y objetivos | X1: Espíritus (agregados) | Y1: Espíritus (detalle) | Z1: Mecánica | AA1: Excluye a
A2: EFE | B2: dinastia_verde | C2: EFE_custodio_de_la_tierra | D2: Custodio de la Tierra | E2: 49 | F2: 100 | G2: 0 | H2: 0 | I2: 0 | J2: 0 | K2: 0 | L2: 0 | M2: 0 | N2: 0 | O2: 0 | P2: 0 | Q2: 0 | R2: 0 | S2: 0 | T2: 0 | U2: 0 | V2: 0 | W2: 0 | X2: 0
A3: EFE | B3: dinastia_verde | C3: EFE_la_hora_de_gaia | D3: La Hora de Gaia | E3: 49 | F3: 100 | G3: 0 | H3: 0 | I3: 0 | J3: 0 | K3: 0 | L3: 0 | M3: 0 | N3: 0 | O3: 0 | P3: 0 | Q3: 0 | R3: 0 | S3: 0 | T3: 0 | U3: 0 | V3: 0 | W3: 0 | X3: 0
A4: EFE | B4: dinastia_verde | C4: EFE_el_mandato_renovado | D4: El Mandato Renovado | E4: 49 | F4: 100 | G4: 0 | H4: 0 | I4: 0 | J4: 0 | K4: 0 | L4: 0 | M4: 0 | N4: 0 | O4: 0 | P4: 0 | Q4: 0 | R4: 0 | S4: 0 | T4: 0 | U4: 0 | V4: 0 | W4: 0 | X4: 0 | AA4: EFE_los_incendios_de_gaia
A5: EFE | B5: dinastia_verde | C5: EFE_la_corte_de_los_bosques | D5: La Corte de los Bosques | E5: 49 | F5: 0 | G5: 0 | H5: 0 | I5: 0 | J5: 0 | K5: 0 | L5: 0 | M5: 0 | N5: 0 | O5: 0 | P5: 0 | Q5: 0 | R5: 0 | S5: 0 | T5: 0 | U5: 0 | V5: 0 | W5: 0 | X5: 1 | Y5: EFE_trono_del_bosque, - EFE_corte_dividida
A6: EFE | B6: dinastia_verde | C6: EFE_heredero_de_la_tierra | D6: Heredero de la Tierra | E6: 84 | F6: 100 | G6: 0 | H6: 0 | I6: 0 | J6: 0 | K6: 0 | L6: 0 | M6: 0 | N6: 0 | O6: 0 | P6: 0 | Q6: 0 | R6: 0 | S6: 0 | T6: 0 | U6: 0 | V6: 0 | W6: 0 | X6: 0 | Z6: EFE_biosteel +2, EFE_saturacion +6
A7: EFE | B7: dinastia_verde | C7: EFE_las_misiones_guaranies | D7: Las Misiones Guaraníes | E7: 63 | F7: 100 | G7: 0 | H7: 0 | I7: 0 | J7: 0 | K7: 0 | L7: 0 | M7: 0 | N7: 0 | O7: 0 | P7: 0 | Q7: 0 | R7: 0 | S7: 0 | T7: 0 | U7: 0 | V7: 0 | W7: 1 | X7: 0
A8: EFE | B8: dinastia_verde | C8: EFE_integrar_la_patagonia | D8: Integrar la Patagonia Austral | E8: 63 | F8: 100 | G8: 0 | H8: 0 | I8: 0 | J8: 0 | K8: 0 | L8: 0 | M8: 0 | N8: 0 | O8: 0 | P8: 0 | Q8: 0 | R8: 0 | S8: 0 | T8: 0 | U8: 0 | V8: 0 | W8: 1 | X8: 0
A9: EFE | B9: dinastia_verde | C9: EFE_la_gran_muralla_verde | D9: La Gran Muralla Verde | E9: 63 | F9: 0 | G9: 0 | H9: 0 | I9: 0 | J9: 0 | K9: 0 | L9: 0 | M9: 0 | N9: 0 | O9: 0 | P9: 0 | Q9: 0 | R9: 0 | S9: 0 | T9: 0 | U9: 0 | V9: 0 | W9: 0 | X9: 1 | Y9: EFE_muralla_verde
A10: EFE | B10: dinastia_verde | C10: EFE_guardian_del_acuifero | D10: Guardián del Acuífero | E10: 49 | F10: 0 | G10: 0 | H10: 0 | I10: 0 | J10: 0 | K10: 0 | L10: 0 | M10: 0 | N10: 0 | O10: 0 | P10: 0 | Q10: 0 | R10: 0 | S10: 0 | T10: 0 | U10: 0 | V10: 0 | W10: 0 | X10: 1 | Y10: EFE_defensa_acuifero
A11: EFE | B11: dinastia_verde | C11: EFE_el_agua_no_se_vende | D11: El Agua no se Vende | E11: 105 | F11: 0 | G11: 0 | H11: 5 | I11: 0 | J11: 0 | K11: 0 | L11: 0 | M11: 0 | N11: 0 | O11: 0 | P11: 0 | Q11: 0 | R11: 0 | S11: 0 | T11: 0 | U11: 0 | V11: 0 | W11: 0 | X11: 0
A12: EFE | B12: dinastia_verde | C12: EFE_la_corona_de_gaia | D12: La Corona de Gaia | E12: 84 | F12: 0 | G12: 0 | H12: 0 | I12: 0 | J12: 0 | K12: 0 | L12: 0 | M12: 0 | N12: 0 | O12: 0 | P12: 0 | Q12: 0 | R12: 0 | S12: 0 | T12: 0 | U12: 0 | V12: 0 | W12: 0 | X12: 1 | Y12: EFE_trono_del_bosque -> EFE_trono_eterno | Z12: EFE_biosteel +3, EFE_saturacion +9
A13: EFE | B13: el_monte | C13: EFE_los_incendios_de_gaia | D13: Los Incendios de Gaia | E13: 35 | F13: 0 | G13: 0 | H13: 0 | I13: 0 | J13: 0 | K13: 0 | L13: 0 | M13: 0 | N13: 0 | O13: 0 | P13: 0 | Q13: 0 | R13: 0 | S13: 0 | T13: 0 | U13: 0 | V13: 0 | W13: 0 | X13: 1 | Y13: EFE_crisis_del_monte (temporal) | AA13: EFE_el_mandato_renovado
A14: EFE | B14: el_monte | C14: EFE_el_monte_se_levanta | D14: El Monte se Levanta | E14: 21 | F14: 0 | G14: 0 | H14: 0 | I14: 0 | J14: 0 | K14: 0 | L14: 0 | M14: 0 | N14: 0 | O14: 0 | P14: 0 | Q14: 0 | R14: 0 | S14: 0 | T14: 0 | U14: 0 | V14: 0 | W14: 0 | X14: 1 | Y14: EFE_mandato_verde -> EFE_mandato_del_monte, - EFE_corte_dividida
A15: EFE | B15: el_monte | C15: EFE_desurbanizar | D15: Desurbanizar | E15: 49 | F15: 0 | G15: 0 | H15: 0 | I15: 30000 | J15: 0 | K15: 0 | L15: 0 | M15: 0 | N15: 0 | O15: 0 | P15: 0 | Q15: 0 | R15: 0 | S15: 0 | T15: 0 | U15: 0 | V15: 0 | W15: 0 | X15: 1 | Y15: EFE_desurbanizacion | Z15: EFE_biosteel +3, EFE_saturacion +9
A16: EFE | B16: el_monte | C16: EFE_el_bosque_es_el_ejercito | D16: El Bosque es el Ejército | E16: 63 | F16: 0 | G16: 0 | H16: 0 | I16: 0 | J16: 0 | K16: 0 | L16: 0 | M16: 0 | N16: 0 | O16: 0 | P16: 0 | Q16: 0 | R16: 0 | S16: 0 | T16: 0 | U16: 0 | V16: 0 | W16: 0 | X16: 1 | Y16: EFE_bosque_armado
A17: EFE | B17: el_monte | C17: EFE_arrasar_la_tierra | D17: Tierra Arrasada | E17: 49 | F17: 0 | G17: 0 | H17: 0 | I17: 0 | J17: 0 | K17: 0 | L17: 0 | M17: 0 | N17: 0 | O17: 0 | P17: 0 | Q17: 0 | R17: 0 | S17: 0 | T17: 0 | U17: 0 | V17: 0 | W17: 0 | X17: 1 | Y17: EFE_tierra_arrasada
A18: EFE | B18: el_monte | C18: EFE_sembrar_la_conquista | D18: Sembrar la Conquista | E18: 84 | F18: 0 | G18: 0 | H18: 0 | I18: 0 | J18: 0 | K18: 0 | L18: 0 | M18: 0 | N18: 0 | O18: 0 | P18: 3 | Q18: 0 | R18: 0 | S18: 0 | T18: 0 | U18: 0 | V18: 0 | W18: 0 | X18: 0 | Z18: EFE_biosteel +2, EFE_saturacion +6
A19: EFE | B19: el_monte | C19: EFE_que_avance_la_selva | D19: La Selva Avanza | E19: 49 | F19: 0 | G19: 0 | H19: 0 | I19: 0 | J19: 0 | K19: 0 | L19: 0 | M19: 0 | N19: 0 | O19: 0 | P19: 0 | Q19: 0 | R19: 0 | S19: 0 | T19: 0 | U19: 0 | V19: 0 | W19: 0 | X19: 1 | Y19: EFE_la_selva_avanza
A20: EFE | B20: el_monte | C20: EFE_la_ofensiva_verde | D20: La Ofensiva Verde | E20: 105 | F20: 0 | G20: 0 | H20: 0 | I20: 0 | J20: 0 | K20: 0 | L20: 0 | M20: 0 | N20: 2 | O20: 0 | P20: 0 | Q20: 0 | R20: 0 | S20: 0 | T20: 0 | U20: 0 | V20: 0 | W20: 1 | X20: 1 | Y20: EFE_ofensiva_verde
A21: EFE | B21: el_monte | C21: EFE_un_continente_vivo | D21: Un Continente Vivo | E21: 84 | F21: 0 | G21: 0 | H21: 0 | I21: 0 | J21: 0 | K21: 0 | L21: 0 | M21: 0 | N21: 0 | O21: 0 | P21: 0 | Q21: 0 | R21: 0 | S21: 0 | T21: 0 | U21: 0 | V21: 0 | W21: 0 | X21: 1 | Y21: EFE_continente_vivo
A22: EFE | B22: destino | C22: EFE_el_concilio_verde | D22: El Concilio Verde | E22: 70 | F22: 120 | G22: 5 | H22: 0 | I22: 0 | J22: 0 | K22: 0 | L22: 0 | M22: 0 | N22: 0 | O22: 0 | P22: 0 | Q22: 0 | R22: 0 | S22: 0 | T22: 0 | U22: 0 | V22: 0 | W22: 0 | X22: 0
A23: EFE | B23: destino | C23: EFE_la_ley_de_la_semilla | D23: La Ley de la Semilla | E23: 70 | F23: 0 | G23: 0 | H23: 0 | I23: 0 | J23: 0 | K23: 0 | L23: 0 | M23: 0 | N23: 0 | O23: 0 | P23: 0 | Q23: 0 | R23: 0 | S23: 0 | T23: 0 | U23: 0 | V23: 0 | W23: 0 | X23: 1 | Y23: EFE_ley_de_la_semilla
A24: EFE | B24: destino | C24: EFE_los_guardianes_del_bosque | D24: Los Guardianes del Bosque | E24: 70 | F24: 0 | G24: 0 | H24: 5 | I24: 0 | J24: 25 | K24: 0 | L24: 0 | M24: 0 | N24: 0 | O24: 0 | P24: 0 | Q24: 0 | R24: 0 | S24: 0 | T24: 0 | U24: 0 | V24: 0 | W24: 0 | X24: 0
A25: EFE | B25: destino | C25: EFE_el_destino_de_gaia | D25: El Destino de Gaia | E25: 105 | F25: 50 | G25: 0 | H25: 0 | I25: 0 | J25: 0 | K25: 0 | L25: 0 | M25: 0 | N25: 0 | O25: 0 | P25: 0 | Q25: 0 | R25: 0 | S25: 0 | T25: 0 | U25: 0 | V25: 0 | W25: 8 | X25: 0
A26: EFE | B26: autarquia | C26: EFE_ministerio_de_restauracion | D26: Ministerio de la Restauración | E26: 49 | F26: 0 | G26: 0 | H26: 0 | I26: 0 | J26: 0 | K26: 0 | L26: 0 | M26: 0 | N26: 0 | O26: 2 | P26: 0 | Q26: 0 | R26: 0 | S26: 0 | T26: 0 | U26: 0 | V26: 0 | W26: 0 | X26: 0 | Y26: - EFE_ciudades_sedientas
A27: EFE | B27: autarquia | C27: EFE_autarquia_del_bioacero | D27: La Autarquía del Bioacero | E27: 63 | F27: 150 | G27: 0 | H27: 0 | I27: 0 | J27: 0 | K27: 0 | L27: 0 | M27: 0 | N27: 0 | O27: 1 | P27: 0 | Q27: 0 | R27: 0 | S27: 0 | T27: 0 | U27: 0 | V27: 0 | W27: 0 | X27: 1 | Y27: EFE_autarquia_estrategica | Z27: EFE_biosteel +1, EFE_saturacion +3 | AA27: EFE_diplomacia_del_agua
A28: EFE | B28: autarquia | C28: EFE_cubas_profundas | D28: Cubas Profundas | E28: 49 | F28: 0 | G28: 0 | H28: 0 | I28: 0 | J28: 0 | K28: 0 | L28: 0 | M28: 0 | N28: 2 | O28: 0 | P28: 0 | Q28: 0 | R28: 0 | S28: 0 | T28: 0 | U28: 0 | V28: 0 | W28: 0 | X28: 0 | Z28: EFE_biosteel +2, EFE_saturacion +6
A29: EFE | B29: autarquia | C29: EFE_bosques_fabrica | D29: Bosques-Fábrica | E29: 49 | F29: 0 | G29: 0 | H29: 0 | I29: 0 | J29: 0 | K29: 0 | L29: 0 | M29: 0 | N29: 0 | O29: 2 | P29: 0 | Q29: 0 | R29: 0 | S29: 0 | T29: 0 | U29: 0 | V29: 0 | W29: 0 | X29: 0
A30: EFE | B30: autarquia | C30: EFE_economia_circular | D30: La Economía Circular | E30: 63 | F30: 100 | G30: 0 | H30: 0 | I30: 0 | J30: 0 | K30: 0 | L30: 0 | M30: 0 | N30: 0 | O30: 0 | P30: 0 | Q30: 0 | R30: 0 | S30: 0 | T30: 0 | U30: 0 | V30: 0 | W30: 0 | X30: 0 | Z30: EFE_biosteel +2, EFE_saturacion +6
A31: EFE | B31: autarquia | C31: EFE_la_autarquia_total | D31: La Autarquía Total | E31: 84 | F31: 0 | G31: 0 | H31: 0 | I31: 0 | J31: 0 | K31: 0 | L31: 0 | M31: 0 | N31: 0 | O31: 0 | P31: 0 | Q31: 0 | R31: 0 | S31: 0 | T31: 0 | U31: 0 | V31: 0 | W31: 0 | X31: 1 | Y31: EFE_autarquia_estrategica -> EFE_autarquia_total
A32: EFE | B32: autarquia | C32: EFE_el_bioacero_soberano | D32: El Bioacero Soberano | E32: 77 | F32: 0 | G32: -5 | H32: 0 | I32: 0 | J32: 0 | K32: 0 | L32: 0 | M32: 0 | N32: 0 | O32: 0 | P32: 2 | Q32: 0 | R32: 0 | S32: 0 | T32: 0 | U32: 0 | V32: 0 | W32: 0 | X32: 0 | Z32: EFE_biosteel +2, EFE_saturacion +6
A33: EFE | B33: autarquia | C33: EFE_la_fortaleza_verde | D33: La Fortaleza Verde | E33: 98 | F33: 0 | G33: 0 | H33: 0 | I33: 0 | J33: 0 | K33: 0 | L33: 0 | M33: 0 | N33: 0 | O33: 0 | P33: 0 | Q33: 0 | R33: 0 | S33: 0 | T33: 0 | U33: 0 | V33: 0 | W33: 0 | X33: 1 | Y33: EFE_autarquia_total -> EFE_fortaleza_verde
A34: EFE | B34: diplomacia_agua | C34: EFE_diplomacia_del_agua | D34: La Diplomacia del Agua | E34: 63 | F34: 0 | G34: 0 | H34: 0 | I34: 0 | J34: 0 | K34: 0 | L34: 0 | M34: 0 | N34: 0 | O34: 0 | P34: 0 | Q34: 0 | R34: 0 | S34: 0 | T34: 0 | U34: 0 | V34: 0 | W34: 0 | X34: 1 | Y34: EFE_diplomacia_hidrica | AA34: EFE_autarquia_del_bioacero
A35: EFE | B35: diplomacia_agua | C35: EFE_bancos_de_semillas | D35: Bancos de Semillas | E35: 49 | F35: 100 | G35: 0 | H35: 0 | I35: 0 | J35: 0 | K35: 0 | L35: 0 | M35: 0 | N35: 0 | O35: 0 | P35: 0 | Q35: 0 | R35: 0 | S35: 0 | T35: 0 | U35: 0 | V35: 0 | W35: 0 | X35: 0
A36: EFE | B36: diplomacia_agua | C36: EFE_tratados_de_agua | D36: Tratados de Agua | E36: 49 | F36: 0 | G36: 0 | H36: 0 | I36: 0 | J36: 0 | K36: 0 | L36: 0 | M36: 0 | N36: 0 | O36: 2 | P36: 0 | Q36: 0 | R36: 0 | S36: 0 | T36: 0 | U36: 0 | V36: 0 | W36: 0 | X36: 0
A37: EFE | B37: diplomacia_agua | C37: EFE_el_acuifero_como_embajada | D37: El Acuífero como Embajada | E37: 63 | F37: 50 | G37: 0 | H37: 0 | I37: 0 | J37: 0 | K37: 0 | L37: 0 | M37: 0 | N37: 0 | O37: 2 | P37: 0 | Q37: 0 | R37: 0 | S37: 0 | T37: 0 | U37: 0 | V37: 0 | W37: 0 | X37: 0
A38: EFE | B38: diplomacia_agua | C38: EFE_la_potencia_hidrica | D38: La Potencia Hídrica | E38: 84 | F38: 0 | G38: 0 | H38: 0 | I38: 0 | J38: 0 | K38: 0 | L38: 0 | M38: 0 | N38: 0 | O38: 0 | P38: 0 | Q38: 0 | R38: 0 | S38: 0 | T38: 0 | U38: 0 | V38: 0 | W38: 0 | X38: 1 | Y38: EFE_diplomacia_hidrica -> EFE_potencia_hidrica
A39: EFE | B39: diplomacia_agua | C39: EFE_los_acueductos_del_continente | D39: Los Acueductos del Continente | E39: 77 | F39: 50 | G39: 0 | H39: 0 | I39: 0 | J39: 0 | K39: 0 | L39: 0 | M39: 0 | N39: 0 | O39: 2 | P39: 0 | Q39: 0 | R39: 0 | S39: 0 | T39: 0 | U39: 0 | V39: 0 | W39: 0 | X39: 0
A40: EFE | B40: diplomacia_agua | C40: EFE_el_agua_de_la_vida | D40: El Agua de la Vida | E40: 98 | F40: 0 | G40: 0 | H40: 0 | I40: 0 | J40: 0 | K40: 0 | L40: 0 | M40: 0 | N40: 0 | O40: 0 | P40: 0 | Q40: 0 | R40: 0 | S40: 0 | T40: 0 | U40: 0 | V40: 0 | W40: 0 | X40: 1 | Y40: EFE_potencia_hidrica -> EFE_agua_de_la_vida | Z40: EFE_saturacion -10
A41: EFE | B41: cubas | C41: EFE_cubas_de_segunda_generacion | D41: Cubas de Segunda Generación | E41: 49 | F41: 0 | G41: 0 | H41: 0 | I41: 0 | J41: 0 | K41: 0 | L41: 0 | M41: 0 | N41: 0 | O41: 2 | P41: 0 | Q41: 0 | R41: 0 | S41: 0 | T41: 0 | U41: 0 | V41: 0 | W41: 0 | X41: 0 | Z41: EFE_biosteel +2, EFE_saturacion +6
A42: EFE | B42: cubas | C42: EFE_biorrefinerias_de_rosario | D42: Las Biorrefinerías de Rosario | E42: 49 | F42: 0 | G42: 0 | H42: 0 | I42: 0 | J42: 0 | K42: 0 | L42: 0 | M42: 0 | N42: 0 | O42: 2 | P42: 0 | Q42: 0 | R42: 0 | S42: 0 | T42: 0 | U42: 0 | V42: 0 | W42: 0 | X42: 0
A43: EFE | B43: cubas | C43: EFE_polo_industrial_de_gaia | D43: El Polo Industrial de Gaia | E43: 63 | F43: 0 | G43: 0 | H43: 0 | I43: 0 | J43: 0 | K43: 0 | L43: 0 | M43: 0 | N43: 1 | O43: 0 | P43: 2 | Q43: 0 | R43: 0 | S43: 0 | T43: 0 | U43: 0 | V43: 0 | W43: 0 | X43: 0
A44: EFE | B44: cubas | C44: EFE_energia_de_biomasa | D44: Energía de Biomasa | E44: 49 | F44: 0 | G44: 0 | H44: 0 | I44: 0 | J44: 0 | K44: 0 | L44: 0 | M44: 0 | N44: 0 | O44: 0 | P44: 0 | Q44: 0 | R44: 0 | S44: 0 | T44: 0 | U44: 0 | V44: 0 | W44: 0 | X44: 1 | Y44: EFE_red_hidrica
A45: EFE | B45: cubas | C45: EFE_astilleros_del_plata | D45: Los Astilleros del Plata | E45: 49 | F45: 0 | G45: 0 | H45: 0 | I45: 0 | J45: 0 | K45: 0 | L45: 0 | M45: 0 | N45: 0 | O45: 0 | P45: 0 | Q45: 2 | R45: 0 | S45: 0 | T45: 0 | U45: 0 | V45: 0 | W45: 0 | X45: 0
A46: EFE | B46: cubas | C46: EFE_laboratorio_de_gaia | D46: El Laboratorio de Gaia | E46: 105 | F46: 0 | G46: 0 | H46: 0 | I46: 0 | J46: 0 | K46: 0 | L46: 0 | M46: 1 | N46: 0 | O46: 0 | P46: 0 | Q46: 0 | R46: 0 | S46: 0 | T46: 0 | U46: 0 | V46: 0 | W46: 0 | X46: 0
A47: EFE | B47: guardia_verde | C47: EFE_guardia_verde_movilizada | D47: La Guardia Verde Movilizada | E47: 49 | F47: 0 | G47: 0 | H47: 0 | I47: 0 | J47: 0 | K47: 0 | L47: 0 | M47: 0 | N47: 0 | O47: 0 | P47: 0 | Q47: 0 | R47: 0 | S47: 0 | T47: 0 | U47: 0 | V47: 0 | W47: 0 | X47: 1 | Y47: EFE_guardia_movilizada, - EFE_guardia_mal_equipada
A48: EFE | B48: guardia_verde | C48: EFE_doctrina_del_condor | D48: La Doctrina del Cóndor | E48: 49 | F48: 0 | G48: 0 | H48: 0 | I48: 0 | J48: 0 | K48: 0 | L48: 0 | M48: 0 | N48: 1 | O48: 0 | P48: 0 | Q48: 0 | R48: 0 | S48: 0 | T48: 0 | U48: 0 | V48: 0 | W48: 0 | X48: 0
A49: EFE | B49: guardia_verde | C49: EFE_legiones_de_iguazu | D49: Las Legiones de Iguazú | E49: 63 | F49: 0 | G49: 0 | H49: 0 | I49: 50000 | J49: 0 | K49: 0 | L49: 0 | M49: 0 | N49: 1 | O49: 0 | P49: 0 | Q49: 0 | R49: 0 | S49: 0 | T49: 0 | U49: 0 | V49: 0 | W49: 0 | X49: 0
A50: EFE | B50: guardia_verde | C50: EFE_entrenamiento_de_montana | D50: Montaña y Selva | E50: 49 | F50: 0 | G50: 0 | H50: 0 | I50: 0 | J50: 0 | K50: 0 | L50: 0 | M50: 0 | N50: 0 | O50: 0 | P50: 0 | Q50: 0 | R50: 0 | S50: 0 | T50: 0 | U50: 0 | V50: 0 | W50: 0 | X50: 1 | Y50: EFE_montana_y_selva
A51: EFE | B51: guardia_verde | C51: EFE_el_mariscal_etchegaray | D51: El Mariscal Etchegaray | E51: 49 | F51: 0 | G51: 0 | H51: 0 | I51: 0 | J51: 75 | K51: 0 | L51: 0 | M51: 0 | N51: 0 | O51: 0 | P51: 0 | Q51: 0 | R51: 0 | S51: 0 | T51: 0 | U51: 0 | V51: 0 | W51: 0 | X51: 0
A52: EFE | B52: guardia_verde | C52: EFE_cultivar_la_armadura | D52: Armadura Viviente | E52: 84 | F52: 0 | G52: 0 | H52: 0 | I52: 0 | J52: 0 | K52: 0 | L52: 0 | M52: 0 | N52: 2 | O52: 0 | P52: 0 | Q52: 0 | R52: 0 | S52: 0 | T52: 0 | U52: 0 | V52: 0 | W52: 0 | X52: 1 | Y52: EFE_armadura_viviente | Z52: EFE_biosteel -3
A53: EFE | B53: condores | C53: EFE_alas_del_condor | D53: Alas del Cóndor | E53: 49 | F53: 0 | G53: 0 | H53: 0 | I53: 0 | J53: 0 | K53: 0 | L53: 0 | M53: 0 | N53: 1 | O53: 0 | P53: 0 | Q53: 0 | R53: 0 | S53: 0 | T53: 0 | U53: 0 | V53: 50 | W53: 0 | X53: 0
A54: EFE | B54: condores | C54: EFE_aerodromos_de_la_pampa | D54: Los Aeródromos de la Pampa | E54: 49 | F54: 0 | G54: 0 | H54: 0 | I54: 0 | J54: 0 | K54: 0 | L54: 25 | M54: 0 | N54: 0 | O54: 0 | P54: 0 | Q54: 0 | R54: 0 | S54: 2 | T54: 0 | U54: 0 | V54: 0 | W54: 0 | X54: 0
A55: EFE | B55: condores | C55: EFE_cazas_de_bioacero | D55: Cazas de Bioacero | E55: 63 | F55: 0 | G55: 0 | H55: 0 | I55: 0 | J55: 0 | K55: 0 | L55: 0 | M55: 0 | N55: 2 | O55: 0 | P55: 0 | Q55: 0 | R55: 0 | S55: 0 | T55: 0 | U55: 0 | V55: 100 | W55: 0 | X55: 0 | Z55: EFE_biosteel -1
A56: EFE | B56: condores | C56: EFE_bombardeo_de_precision | D56: Bombardeo de Precisión | E56: 49 | F56: 0 | G56: 0 | H56: 0 | I56: 0 | J56: 0 | K56: 0 | L56: 0 | M56: 0 | N56: 1 | O56: 0 | P56: 0 | Q56: 0 | R56: 0 | S56: 0 | T56: 0 | U56: 0 | V56: 0 | W56: 0 | X56: 0
A57: EFE | B57: condores | C57: EFE_cielo_de_gaia | D57: El Cielo de Gaia | E57: 49 | F57: 0 | G57: 0 | H57: 5 | I57: 0 | J57: 0 | K57: 0 | L57: 50 | M57: 0 | N57: 0 | O57: 0 | P57: 0 | Q57: 0 | R57: 0 | S57: 0 | T57: 0 | U57: 0 | V57: 0 | W57: 0 | X57: 0
A58: EFE | B58: condores | C58: EFE_flotilla_del_plata | D58: La Flotilla del Plata | E58: 84 | F58: 0 | G58: 0 | H58: 0 | I58: 0 | J58: 0 | K58: 0 | L58: 0 | M58: 0 | N58: 1 | O58: 0 | P58: 0 | Q58: 2 | R58: 0 | S58: 0 | T58: 0 | U58: 0 | V58: 0 | W58: 0 | X58: 0
A59: EFE | B59: ciclo_bioacero | C59: EFE_primera_cosecha | D59: La Primera Cosecha | E59: 35 | F59: 0 | G59: 0 | H59: 0 | I59: 0 | J59: 0 | K59: 0 | L59: 0 | M59: 0 | N59: 0 | O59: 0 | P59: 0 | Q59: 0 | R59: 0 | S59: 0 | T59: 0 | U59: 0 | V59: 0 | W59: 0 | X59: 0 | Z59: EFE_biosteel +1, EFE_saturacion +3
A60: EFE | B60: ciclo_bioacero | C60: EFE_biosteel_umbral_1 | D60: Carrera del Bioacero: Nivel 1 | E60: 63 | F60: 0 | G60: 0 | H60: 0 | I60: 0 | J60: 0 | K60: 0 | L60: 0 | M60: 0 | N60: 0 | O60: 0 | P60: 0 | Q60: 0 | R60: 0 | S60: 0 | T60: 0 | U60: 0 | V60: 0 | W60: 0 | X60: 1 | Y60: EFE_biosteel_t1
A61: EFE | B61: ciclo_bioacero | C61: EFE_cepa_endurecida | D61: La Cepa Endurecida | E61: 49 | F61: 50 | G61: 0 | H61: 0 | I61: 0 | J61: 0 | K61: 0 | L61: 0 | M61: 0 | N61: 0 | O61: 0 | P61: 0 | Q61: 0 | R61: 0 | S61: 0 | T61: 0 | U61: 0 | V61: 0 | W61: 0 | X61: 0 | Z61: EFE_biosteel +2, EFE_saturacion +6
A62: EFE | B62: ciclo_bioacero | C62: EFE_biosteel_umbral_2 | D62: Carrera del Bioacero: Nivel 2 | E62: 63 | F62: 0 | G62: 0 | H62: 0 | I62: 0 | J62: 0 | K62: 0 | L62: 0 | M62: 0 | N62: 0 | O62: 0 | P62: 0 | Q62: 0 | R62: 0 | S62: 0 | T62: 0 | U62: 0 | V62: 0 | W62: 0 | X62: 1 | Y62: EFE_biosteel_t1 -> EFE_biosteel_t2
A63: EFE | B63: ciclo_bioacero | C63: EFE_exportar_semillas | D63: Exportar las Semillas | E63: 49 | F63: 100 | G63: 0 | H63: 0 | I63: 0 | J63: 0 | K63: 0 | L63: 0 | M63: 0 | N63: 0 | O63: 0 | P63: 0 | Q63: 0 | R63: 0 | S63: 0 | T63: 0 | U63: 0 | V63: 0 | W63: 0 | X63: 0
A64: EFE | B64: ciclo_bioacero | C64: EFE_biosteel_umbral_3 | D64: Carrera del Bioacero: Nivel 3 | E64: 84 | F64: 0 | G64: 0 | H64: 0 | I64: 0 | J64: 0 | K64: 0 | L64: 0 | M64: 0 | N64: 0 | O64: 0 | P64: 0 | Q64: 0 | R64: 0 | S64: 0 | T64: 0 | U64: 0 | V64: 0 | W64: 0 | X64: 1 | Y64: EFE_biosteel_t2 -> EFE_biosteel_t3
A65: EFE | B65: ciclo_bioacero | C65: EFE_el_metal_que_crece | D65: El Metal que Crece | E65: 105 | F65: 0 | G65: 0 | H65: 0 | I65: 0 | J65: 0 | K65: 0 | L65: 0 | M65: 1 | N65: 0 | O65: 0 | P65: 0 | Q65: 0 | R65: 0 | S65: 0 | T65: 0 | U65: 0 | V65: 0 | W65: 0 | X65: 0 | Z65: EFE_biosteel +5, EFE_saturacion +15
A66: EFE | B66: cubas_sanas | C66: EFE_rotar_los_cultivos | D66: Rotar los Cultivos | E66: 49 | F66: 0 | G66: 0 | H66: 0 | I66: 0 | J66: 0 | K66: 0 | L66: 0 | M66: 0 | N66: 0 | O66: 0 | P66: 0 | Q66: 0 | R66: 0 | S66: 0 | T66: 0 | U66: 0 | V66: 0 | W66: 0 | X66: 1 | Y66: EFE_rotacion_de_cultivos | Z66: EFE_saturacion -15
A67: EFE | B67: cubas_sanas | C67: EFE_laboratorios_del_micelio | D67: Laboratorios del Micelio | E67: 49 | F67: 0 | G67: 0 | H67: 0 | I67: 0 | J67: 0 | K67: 0 | L67: 0 | M67: 0 | N67: 1 | O67: 0 | P67: 0 | Q67: 0 | R67: 0 | S67: 0 | T67: 0 | U67: 0 | V67: 0 | W67: 0 | X67: 0 | Z67: EFE_saturacion -10
A68: EFE | B68: cubas_sanas | C68: EFE_cubas_de_contencion | D68: Cubas de Contención | E68: 63 | F68: 0 | G68: 0 | H68: 0 | I68: 0 | J68: 0 | K68: 0 | L68: 0 | M68: 0 | N68: 0 | O68: 2 | P68: 0 | Q68: 0 | R68: 0 | S68: 0 | T68: 0 | U68: 0 | V68: 0 | W68: 0 | X68: 0 | Z68: EFE_saturacion -10
A69: EFE | B69: cubas_sanas | C69: EFE_el_bioacero_domesticado | D69: El Bioacero Domesticado | E69: 84 | F69: 0 | G69: 0 | H69: 0 | I69: 0 | J69: 0 | K69: 0 | L69: 0 | M69: 0 | N69: 0 | O69: 0 | P69: 0 | Q69: 0 | R69: 0 | S69: 0 | T69: 0 | U69: 0 | V69: 0 | W69: 0 | X69: 1 | Y69: EFE_espiritu_bioacero_domesticado
A70: EFE | B70: cubas_sanas | C70: EFE_exportar_el_bioacero | D70: Exportar el Bioacero | E70: 63 | F70: 100 | G70: 0 | H70: 0 | I70: 0 | J70: 0 | K70: 0 | L70: 0 | M70: 0 | N70: 0 | O70: 0 | P70: 0 | Q70: 0 | R70: 0 | S70: 0 | T70: 0 | U70: 0 | V70: 0 | W70: 0 | X70: 0
A71: EFE | B71: cubas_sanas | C71: EFE_la_selva_de_acero | D71: La Selva de Acero | E71: 105 | F71: 0 | G71: 0 | H71: 0 | I71: 0 | J71: 0 | K71: 0 | L71: 0 | M71: 0 | N71: 1 | O71: 0 | P71: 0 | Q71: 0 | R71: 0 | S71: 0 | T71: 0 | U71: 0 | V71: 0 | W71: 0 | X71: 1 | Y71: EFE_espiritu_selva_de_acero
A72: ASC | B72: consejo_sorteado | C72: ASC_el_ano_del_plan | D72: El Año del Plan | E72: 49 | F72: 100 | G72: 0 | H72: 0 | I72: 0 | J72: 0 | K72: 0 | L72: 0 | M72: 0 | N72: 0 | O72: 0 | P72: 0 | Q72: 0 | R72: 0 | S72: 0 | T72: 0 | U72: 0 | V72: 0 | W72: 0 | X72: 0 | Z72: ASC_computo +5
A73: ASC | B73: consejo_sorteado | C73: ASC_la_sesion_del_consejo | D73: El Consejo en Sesión | E73: 49 | F73: 100 | G73: 0 | H73: 0 | I73: 0 | J73: 0 | K73: 0 | L73: 0 | M73: 0 | N73: 0 | O73: 0 | P73: 0 | Q73: 0 | R73: 0 | S73: 0 | T73: 0 | U73: 0 | V73: 0 | W73: 0 | X73: 0
A74: ASC | B74: consejo_sorteado | C74: ASC_el_sorteo_del_ano | D74: El Sorteo del Año | E74: 49 | F74: 100 | G74: 0 | H74: 0 | I74: 0 | J74: 0 | K74: 0 | L74: 0 | M74: 0 | N74: 0 | O74: 0 | P74: 0 | Q74: 0 | R74: 0 | S74: 0 | T74: 0 | U74: 0 | V74: 0 | W74: 0 | X74: 0 | AA74: ASC_el_silencio_del_consejo
A75: ASC | B75: consejo_sorteado | C75: ASC_transparencia_del_plan | D75: Transparencia del Plan | E75: 49 | F75: 0 | G75: 0 | H75: 0 | I75: 0 | J75: 0 | K75: 0 | L75: 0 | M75: 0 | N75: 0 | O75: 0 | P75: 0 | Q75: 0 | R75: 0 | S75: 0 | T75: 0 | U75: 0 | V75: 0 | W75: 0 | X75: 1 | Y75: ASC_transparencia
A76: ASC | B76: consejo_sorteado | C76: ASC_el_derecho_a_no_trabajar | D76: El Derecho a No Trabajar | E76: 63 | F76: 0 | G76: 0 | H76: 0 | I76: 0 | J76: 0 | K76: 0 | L76: 0 | M76: 0 | N76: 0 | O76: 0 | P76: 0 | Q76: 0 | R76: 0 | S76: 0 | T76: 0 | U76: 0 | V76: 0 | W76: 0 | X76: 1 | Y76: ASC_derecho_a_no_trabajar
A77: ASC | B77: consejo_sorteado | C77: ASC_el_consejo_amplia_la_sala | D77: El Consejo Amplía la Sala | E77: 63 | F77: 0 | G77: 0 | H77: 0 | I77: 0 | J77: 0 | K77: 0 | L77: 0 | M77: 0 | N77: 0 | O77: 0 | P77: 0 | Q77: 0 | R77: 0 | S77: 0 | T77: 0 | U77: 0 | V77: 0 | W77: 0 | X77: 1 | Y77: ASC_consejo_ampliado
A78: ASC | B78: consejo_sorteado | C78: ASC_la_paz_de_la_abundancia | D78: La Paz de la Abundancia | E78: 49 | F78: 0 | G78: 0 | H78: 0 | I78: 0 | J78: 0 | K78: 0 | L78: 0 | M78: 0 | N78: 0 | O78: 0 | P78: 0 | Q78: 0 | R78: 0 | S78: 0 | T78: 0 | U78: 0 | V78: 0 | W78: 0 | X78: 1 | Y78: ASC_paz_de_la_abundancia
A79: ASC | B79: consejo_sorteado | C79: ASC_la_liberacion_del_este | D79: La Liberación del Este | E79: 105 | F79: 0 | G79: 0 | H79: 5 | I79: 0 | J79: 50 | K79: 0 | L79: 0 | M79: 0 | N79: 0 | O79: 0 | P79: 0 | Q79: 0 | R79: 0 | S79: 0 | T79: 0 | U79: 0 | V79: 0 | W79: 1 | X79: 0
A80: ASC | B80: consejo_sorteado | C80: ASC_la_comuna_de_los_humanos | D80: La Comuna de los Humanos | E80: 84 | F80: 0 | G80: 0 | H80: 0 | I80: 0 | J80: 0 | K80: 0 | L80: 0 | M80: 1 | N80: 0 | O80: 0 | P80: 0 | Q80: 0 | R80: 0 | S80: 0 | T80: 0 | U80: 0 | V80: 0 | W80: 0 | X80: 1 | Y80: ASC_transparencia -> ASC_comuna_de_los_humanos
A81: ASC | B81: plan_41 | C81: ASC_el_silencio_del_consejo | D81: El Silencio del Consejo | E81: 35 | F81: 0 | G81: 0 | H81: 0 | I81: 0 | J81: 0 | K81: 0 | L81: 0 | M81: 0 | N81: 0 | O81: 0 | P81: 0 | Q81: 0 | R81: 0 | S81: 0 | T81: 0 | U81: 0 | V81: 0 | W81: 0 | X81: 0 | AA81: ASC_el_sorteo_del_ano
A82: ASC | B82: plan_41 | C82: ASC_la_singularidad_del_plan | D82: La Singularidad del Plan | E82: 63 | F82: 0 | G82: 0 | H82: 0 | I82: 0 | J82: 0 | K82: 0 | L82: 0 | M82: 0 | N82: 0 | O82: 0 | P82: 0 | Q82: 0 | R82: 0 | S82: 0 | T82: 0 | U82: 0 | V82: 0 | W82: 0 | X82: 1 | Y82: ASC_singularidad | Z82: ASC_computo +10
A83: ASC | B83: plan_41 | C83: ASC_optimizacion_total | D83: Optimización Total | E83: 49 | F83: 0 | G83: 0 | H83: 0 | I83: 0 | J83: 0 | K83: 0 | L83: 0 | M83: 0 | N83: 0 | O83: 0 | P83: 0 | Q83: 0 | R83: 0 | S83: 0 | T83: 0 | U83: 0 | V83: 0 | W83: 0 | X83: 1 | Y83: ASC_espiritu_optimizacion_total
A84: ASC | B84: plan_41 | C84: ASC_humanos_redundantes | D84: Humanos Redundantes | E84: 63 | F84: 0 | G84: 0 | H84: 0 | I84: 100000 | J84: 0 | K84: 0 | L84: 0 | M84: 0 | N84: 1 | O84: 0 | P84: 0 | Q84: 0 | R84: 0 | S84: 0 | T84: 0 | U84: 0 | V84: 0 | W84: 0 | X84: 0
A85: ASC | B85: plan_41 | C85: ASC_ejercito_sin_bajas | D85: El Ejército sin Bajas | E85: 84 | F85: 0 | G85: 0 | H85: 0 | I85: 0 | J85: 0 | K85: 0 | L85: 0 | M85: 0 | N85: 0 | O85: 0 | P85: 0 | Q85: 0 | R85: 0 | S85: 0 | T85: 0 | U85: 0 | V85: 0 | W85: 0 | X85: 1 | Y85: ASC_espiritu_ejercito_sin_bajas
A86: ASC | B86: plan_41 | C86: ASC_la_reserva_de_silicio | D86: La Reserva de Silicio | E86: 49 | F86: 0 | G86: 0 | H86: 0 | I86: 0 | J86: 0 | K86: 0 | L86: 0 | M86: 0 | N86: 1 | O86: 0 | P86: 0 | Q86: 0 | R86: 0 | S86: 0 | T86: 0 | U86: 0 | V86: 0 | W86: 0 | X86: 0 | Z86: ASC_computo +10
A87: ASC | B87: plan_41 | C87: ASC_el_plan_se_extiende | D87: El Plan se Extiende | E87: 63 | F87: 100 | G87: 0 | H87: 0 | I87: 0 | J87: 0 | K87: 0 | L87: 0 | M87: 0 | N87: 0 | O87: 0 | P87: 0 | Q87: 0 | R87: 0 | S87: 0 | T87: 0 | U87: 0 | V87: 0 | W87: 0 | X87: 0 | Z87: ASC_computo +5
A88: ASC | B88: plan_41 | C88: ASC_convergencia | D88: Convergencia | E88: 84 | F88: 0 | G88: 0 | H88: 0 | I88: 0 | J88: 0 | K88: 0 | L88: 0 | M88: 1 | N88: 0 | O88: 0 | P88: 0 | Q88: 0 | R88: 0 | S88: 0 | T88: 0 | U88: 0 | V88: 0 | W88: 0 | X88: 0 | Z88: ASC_computo +15
A89: ASC | B89: plan_41 | C89: ASC_asignar_africa | D89: Asignar África | E89: 105 | F89: 0 | G89: 0 | H89: 5 | I89: 0 | J89: 0 | K89: 0 | L89: 0 | M89: 0 | N89: 0 | O89: 0 | P89: 0 | Q89: 0 | R89: 0 | S89: 0 | T89: 0 | U89: 0 | V89: 0 | W89: 0 | X89: 0
A90: ASC | B90: destino | C90: ASC_la_asamblea_de_los_datos | D90: La Asamblea de los Datos | E90: 70 | F90: 120 | G90: 5 | H90: 0 | I90: 0 | J90: 0 | K90: 0 | L90: 0 | M90: 0 | N90: 0 | O90: 0 | P90: 0 | Q90: 0 | R90: 0 | S90: 0 | T90: 0 | U90: 0 | V90: 0 | W90: 0 | X90: 0
A91: ASC | B91: destino | C91: ASC_el_plan_de_silicio | D91: El Plan de Silicio | E91: 70 | F91: 0 | G91: 0 | H91: 0 | I91: 0 | J91: 0 | K91: 0 | L91: 0 | M91: 0 | N91: 0 | O91: 0 | P91: 0 | Q91: 0 | R91: 0 | S91: 0 | T91: 0 | U91: 0 | V91: 0 | W91: 0 | X91: 1 | Y91: ASC_plan_de_silicio
A92: ASC | B92: destino | C92: ASC_la_abundancia_armada | D92: La Abundancia Armada | E92: 70 | F92: 0 | G92: 0 | H92: 5 | I92: 0 | J92: 25 | K92: 0 | L92: 0 | M92: 0 | N92: 0 | O92: 0 | P92: 0 | Q92: 0 | R92: 0 | S92: 0 | T92: 0 | U92: 0 | V92: 0 | W92: 0 | X92: 0
A93: ASC | B93: destino | C93: ASC_el_destino_de_la_comuna | D93: El Destino de la Comuna | E93: 105 | F93: 50 | G93: 0 | H93: 0 | I93: 0 | J93: 0 | K93: 0 | L93: 0 | M93: 0 | N93: 0 | O93: 0 | P93: 0 | Q93: 0 | R93: 0 | S93: 0 | T93: 0 | U93: 0 | V93: 0 | W93: 7 | X93: 0
A94: ASC | B94: plan_total | C94: ASC_el_consejo_economico | D94: El Consejo Económico | E94: 49 | F94: 0 | G94: 0 | H94: 0 | I94: 0 | J94: 0 | K94: 0 | L94: 0 | M94: 0 | N94: 0 | O94: 2 | P94: 0 | Q94: 0 | R94: 0 | S94: 0 | T94: 0 | U94: 0 | V94: 0 | W94: 0 | X94: 0
A95: ASC | B95: plan_total | C95: ASC_el_plan_total | D95: El Plan Total | E95: 63 | F95: 0 | G95: 0 | H95: 0 | I95: 0 | J95: 0 | K95: 0 | L95: 0 | M95: 0 | N95: 0 | O95: 0 | P95: 0 | Q95: 0 | R95: 0 | S95: 0 | T95: 0 | U95: 0 | V95: 0 | W95: 0 | X95: 1 | Y95: ASC_plan_total | AA95: ASC_el_mercado_de_creditos_de_computo
A96: ASC | B96: plan_total | C96: ASC_cuotas_quinquenales | D96: Cuotas Quinquenales | E96: 49 | F96: 0 | G96: 0 | H96: 0 | I96: 0 | J96: 0 | K96: 0 | L96: 0 | M96: 0 | N96: 0 | O96: 2 | P96: 0 | Q96: 0 | R96: 0 | S96: 0 | T96: 0 | U96: 0 | V96: 0 | W96: 0 | X96: 0
A97: ASC | B97: plan_total | C97: ASC_asignacion_por_necesidad | D97: Asignación por Necesidad | E97: 49 | F97: 100 | G97: 0 | H97: 0 | I97: 0 | J97: 0 | K97: 0 | L97: 0 | M97: 0 | N97: 0 | O97: 0 | P97: 0 | Q97: 0 | R97: 0 | S97: 0 | T97: 0 | U97: 0 | V97: 0 | W97: 0 | X97: 0
A98: ASC | B98: plan_total | C98: ASC_el_gran_calculo | D98: El Gran Cálculo | E98: 63 | F98: 0 | G98: 0 | H98: 0 | I98: 0 | J98: 0 | K98: 0 | L98: 0 | M98: 0 | N98: 0 | O98: 0 | P98: 2 | Q98: 0 | R98: 0 | S98: 0 | T98: 0 | U98: 0 | V98: 0 | W98: 0 | X98: 0 | Z98: ASC_computo +5
A99: ASC | B99: plan_total | C99: ASC_la_economia_sin_precios | D99: La Economía sin Precios | E99: 84 | F99: 0 | G99: 0 | H99: 0 | I99: 0 | J99: 0 | K99: 0 | L99: 0 | M99: 0 | N99: 0 | O99: 3 | P99: 0 | Q99: 0 | R99: 0 | S99: 0 | T99: 0 | U99: 0 | V99: 0 | W99: 0 | X99: 0
A100: ASC | B100: plan_total | C100: ASC_las_granjas_automaticas | D100: Las Granjas Automáticas | E100: 77 | F100: 0 | G100: 0 | H100: 0 | I100: 0 | J100: 0 | K100: 0 | L100: 0 | M100: 0 | N100: 0 | O100: 2 | P100: 0 | Q100: 0 | R100: 0 | S100: 0 | T100: 0 | U100: 0 | V100: 0 | W100: 0 | X100: 0 | Z100: ASC_computo +5
...

Sheet Espíritus
A1: Modificador | B1: Peso (por +100%) | C1: EFE | D1: ASC | E1: FCU | F1: HSN | G1: NAS | H1: SHD | I1: APF | J1: NRE | K1: ZWB | L1: ZWE | M1: ZWI | N1: ZWM | O1: ZAN | P1: JUNTA
A2: air_ace_bonuses_factor | B2: 100 | C2: 0 | D2: 0 | E2: 0 | F2: 0 | G2: 0.25 | H2: 0 | I2: 0 | J2: 0 | K2: 0 | L2: 0 | M2: 0 | N2: 0 | O2: 0 | P2: 0
A3: air_ace_generation_chance_factor | B3: 100 | C3: 0 | D3: 0 | E3: 0 | F3: 0 | G3: 0.5 | H3: 0 | I3: 0 | J3: 0 | K3: 0 | L3: 0 | M3: 0 | N3: 0 | O3: 0 | P3: 0
A4: air_agility_factor | B4: 400 | C4: 0 | D4: 0 | E4: 0 | F4: 0 | G4: 0.05 | H4: 0 | I4: 0 | J4: 0 | K4: 0 | L4: 0 | M4: 0 | N4: 0 | O4: 0 | P4: 0
A5: air_attack_factor | B5: 400 | C5: 0 | D5: 0 | E5: 0 | F5: 0 | G5: 0.05 | H5: 0 | I5: 0 | J5: 0 | K5: 0 | L5: 0 | M5: 0 | N5: 0 | O5: 0 | P5: 0
A6: air_defence_factor | B6: 400 | C6: 0 | D6: 0 | E6: 0 | F6: 0 | G6: 0.15 | H6: 0 | I6: 0 | J6: 0 | K6: 0 | L6: 0 | M6: 0 | N6: 0 | O6: 0 | P6: 0
A7: air_interception_detect_factor | B7: 200 | C7: 0 | D7: 0 | E7: 0 | F7: 0 | G7: 0.15 | H7: 0 | I7: 0 | J7: 0 | K7: 0 | L7: 0 | M7: 0 | N7: 0 | O7: 0 | P7: 0
A8: air_superiority_efficiency | B8: 400 | C8: 0 | D8: 0 | E8: 0 | F8: 0 | G8: 0.1 | H8: 0 | I8: 0 | J8: 0 | K8: 0 | L8: 0 | M8: 0 | N8: 0 | O8: 0 | P8: 0
A9: army_armor_attack_factor | B9: 500 | C9: 0.3 | D9: 0 | E9: 0 | F9: 0 | G9: 0 | H9: 0 | I9: 0 | J9: 0 | K9: 0 | L9: 0 | M9: 0 | N9: 0 | O9: 0 | P9: 0.15
A10: army_armor_defence_factor | B10: 500 | C10: 0.35 | D10: 0 | E10: 0 | F10: 0 | G10: 0 | H10: 0 | I10: 0 | J10: 0 | K10: 0 | L10: 0 | M10: 0 | N10: 0 | O10: 0 | P10: 0
A11: army_attack_factor | B11: 1500 | C11: 0.35 | D11: 0.2 | E11: 0.2 | F11: 0.15 | G11: 0.3 | H11: 0.2 | I11: 0.25 | J11: 0.3 | K11: 0 | L11: 0.33 | M11: 0 | N11: 0.26 | O11: 0 | P11: 0.1
A12: army_defence_factor | B12: 1200 | C12: 0.6 | D12: 0.05 | E12: 0.05 | F12: 0.05 | G12: 0.3 | H12: 0.15 | I12: 0.15 | J12: 0.3 | K12: 0.36 | L12: 0.35 | M12: 0.35 | N12: 0.43 | O12: 0 | P12: 0.55
A13: army_org_factor | B13: 1000 | C13: 0.28 | D13: 0.1 | E13: 0.23 | F13: 0.05 | G13: 0.25 | H13: 0.33 | I13: 0.25 | J13: 0.45 | K13: 0.2 | L13: 0.25 | M13: 0.25 | N13: 0.25 | O13: 0 | P13: 0.1
... A34: war_support_factor | B34: 800 | C34: 0.35 | D34: 0.05 | E34: 0.2 | F34: 0.25 | G34: 0.15 | H34: 0.2 | I34: 0.35 | J34: 0.23 | K34: 0.21 | L34: 0.41 | M34: 0.41 | N34: 0.41 | O34: 0 | P34: 0
A35: Puntaje de espíritus | C35: =SUMPRODUCT($B$2:$B$34,C2:C34) -> 4826 | D35: =SUMPRODUCT($B$2:$B$34,D2:D34) -> 5590.5 | E35: =SUMPRODUCT($B$2:$B$34,E2:E34) -> 4468.5 | F35: =SUMPRODUCT($B$2:$B$34,F2:F34) -> 3207.5 | G35: =SUMPRODUCT($B$2:$B$34,G2:G34) -> 5172.5 | H35: =SUMPRODUCT($B$2:$B$34,H2:H34) -> 4694.5 | I35: =SUMPRODUCT($B$2:$B$34,I2:I34) -> 5479.5 | J35: =SUMPRODUCT($B$2:$B$34,J2:J34) -> 5722 | ... P35: =SUMPRODUCT($B$2:$B$34,P2:P34) -> 1335

Sheet Pesos
A1: Beneficio | B1: Peso (puntos por unidad) | C1: Qué significa
A2: Días | B2: 0 | C2: 0: los días no suman puntos
A3: Poder político | B3: 1 | C3: 1 punto por cada poder político
A4: Estabilidad (%) | B4: 10 | C4: por cada 1% de estabilidad
A5: Apoyo a la guerra (%) | B5: 8 | C5: por cada 1% de apoyo a la guerra
A6: Mano de obra | B6: 0.002 | C6: por cada hombre (500 hombres = 1 punto)
A7: Exp. ejército | B7: 1
A8: Exp. naval | B8: 1
A9: Exp. aérea | B9: 1
A10: Casillas de investigación | B10: 300 | C10: por cada casilla de investigación
A11: Bonos de tecnología (usos) | B11: 25 | C11: por cada uso de bono de tecnología
A12: Fábricas civiles | B12: 100 | C12: por cada fábrica civil
A13: Fábricas militares | B13: 80 | C13: por cada fábrica militar
A14: Astilleros | B14: 60 | C14: por cada astillero
A15: Infraestructura | B15: 15
A16: Otros edificios (niveles) | B16: 10
A17: Equipo (unidades) | B17: 0.02 | C17: por cada unidad de equipo (50 = 1 punto)
A18: Divisiones | B18: 40 | C18: por cada división
A19: Cazas gratis | B19: 0.5 | C19: por cada caza
A20: Reclamos, núcleos y objetivos | B20: 20
A21: Espíritus (agregados) | B21: 0 | C21: 0: los espíritus se valoran por sus efectos, con los pesos de la hoja Espíritus

Sheet Notas
A1: Cómo se cuenta (generado por tools/focos_balance.py desde spec/07_focus_trees.yaml):
A2: - Se suman TODOS los focos de cada árbol, aunque algunos sean excluyentes (columna 'Excluye a').
A3: - 'Estabilidad' y 'Apoyo a la guerra' son los puntos que se suman en el acto (no los de los espíritus).
A4: - Un 'states' al azar cuenta como 1 región; dentro de un 'if' cuenta solo lo de 'then'.
A5: - Un 'random' cuenta el promedio pesado de sus opciones.
A6: - 'Espíritus' (hoja) es la suma neta de modificadores de los espíritus permanentes que dejan los focos:
A7: agregados menos quitados (los reemplazos por nivel cuentan solo el último). Los temporales no suman.
A8: - Los espíritus vivos que dependen de una variable de la mecánica no tienen valor fijo: no suman.
A9: - No incluye la repoblación (depende del mapa instalado) ni lo que dan los eventos que disparan los focos.
A10: - 'Puntaje en el acto' = suma de cada beneficio por su peso de la hoja Pesos (celdas amarillas, editables).
A11: - 'Puntaje de espíritus' = cada modificador neto por su peso de la hoja Espíritus (columna B, amarilla).
A12: - Los pesos son inventados para comparar con una misma vara; no salen del juego. Cambialos a gusto.
... A14: - Las anarquías, las Tierras Sin Ley (ZAN) y la Junta tienen árboles cortos: no se comparan con las potencias.
